Workbook

Sheet Income & exp 12 months new appr
A2: This Income & Expenditure Report takes its balance from a landlord account statement that has no error corrections. Errors do happen in accounting activities daily, and we cannot assume that everything will work out smooothy without errors.
A3: The next tab is the same Income and Expenditure report, but it derives its income from a distorted Landlord Statement credit-side total.
A5: NEW APPROACH DERIVING LEVY INCOME FROM AN UNCOMPROMISED SOURCE
A7: SUNSET VILLAS
A8: INCOME AND EXPENDITURE FOR THE PERIOD ENDING 31 DEC 2025
A11: INCOME | B11: January | D11: February | F11: March | H11: April | J11: May | L11: June | N11: July | P11: August | R11: September | T11: October | V11: November | X11: December
B12: USD | C12: ZWG | D12: USD | E12: ZWG | F12: USD | G12: ZWG | H12: USD | I12: ZWG | J12: USD | K12: ZWG | L12: USD | M12: ZWG | N12: USD | O12: ZWG | P12: USD | Q12: ZWG | R12: USD | S12: ZWG | T12: USD | U12: ZWG | V12: USD | W12: ZWG | X12: USD | Y12: ZWG
A13: Balance b/forward | B13: 15 | C13: 0 | D13: =B29 -> 5.317 | E13: =C29 -> 0 | F13: =D29 -> 204.712 | G13: =E29 -> 0 | H13: =F29 -> 476.626 | I13: =G29 -> 0 | J13: =H29 -> -501.929 | K13: =I29 -> 0 | ... Y13: =W29 -> 0
A14: Levies | B14: =January!E42 -> 730 | C14: =JUNE!N11 -> 0 | D14: =FEB!E41 -> 1050 | E14: =FEB!M11 -> 0 | F14: ='MARCH 25'!E47 -> 860 | G14: =E30 -> 0 | H14: ='April 25'!E38 -> 550 | I14: 0 | J14: ='May25'!E46 -> 1067 | K14: ='May25'!N11 -> 0 | L14: =june25!E50 -> 1020 | M14: 0 | N14: ='july 25'!E44 -> 708 | O14: 0 | P14: =August25!E36 -> 650 | Q14: 0 | R14: =Sept!E44 -> 750 | S14: =Sept!N11 -> 0 | T14: =October25!E67 -> 1470 | U14: 0 | V14: ='NOV 25'!E31 -> 550 | W14: 0 | X14: ='LANDLORD ACC DETAILED VIEW-LEVY'!G43 -> 1245.52 | Y14: 0
A16: Amount before Expenditure | B16: =SUM(B13:B15) -> 745 | C16: =SUM(C13:C15) -> 0 | D16: =SUM(D13:D15) -> 1055.317 | E16: =SUM(E13:E15) -> 0 | F16: =SUM(F13:F15) -> 1064.712 | G16: =SUM(G13:G15) -> 0 | H16: =SUM(H13:H15) -> 1026.626 | I16: =SUM(I13:I15) -> 0 | ... Y16: =SUM(Y13:Y15) -> 0
A18: EXPENDITURE
A19: Repairs and maintanance | B19: =50+80 -> 130 | C19: 0 | D19: 0 | E19: 0 | F19: =30+140+276 -> 446 | G19: 0 | H19: 275 | I19: 0 | J19: =45+15+58 -> 118 | K19: 0 | L19: =58+20 -> 78 | M19: 0 | N19: =63+67 -> 130 | O19: 0 | P19: 0 | Q19: 0 | R19: 0 | S19: 0 | T19: =138+20 -> 158 | U19: 0 | V19: 60 | W19: 0 | X19: 0 | Y19: 0
A20: Electricity | B20: 0 | C20: 0 | D20: 150 | E20: 0 | G20: 0 | I20: 0 | K20: 0 | L20: 200 | M20: 0 | N20: 0 | O20: 0 | P20: 0 | Q20: 0 | R20: 10 | S20: 0 | T20: 0 | U20: 0 | V20: 200 | W20: 0 | X20: 0 | Y20: 0
A21: Utilities | B21: 10 | C21: 0 | D21: 0 | E21: 0 | F21: 13 | G21: 0 | H21: 5 | I21: 0 | K21: 0 | M21: 0 | N21: 0 | O21: 0 | P21: 0 | Q21: 0 | R21: 0 | S21: 0 | T21: 2.7 | U21: 0 | V21: 0 | W21: 0 | X21: 95.5 | Y21: 0
A22: Salaries | B22: =456+34.11 -> 490.11 | C22: 0 | D22: 543 | E22: 0 | G22: 0 | H22: =543+543 -> 1086 | I22: 0 | J22: 543 | K22: 0 | L22: 543 | M22: 0 | N22: 543 | O22: 0 | P22: 0 | Q22: 0 | R22: 543 | S22: 0 | T22: 543 | U22: 0 | V22: 543 | W22: 0 | X22: 543 | Y22: 0
A23: Security | R23: 90 | S23: 0 | T23: 0 | U23: 0 | V23: 0 | W23: 0 | X23: 0 | Y23: 0
A24: Upper Manyame rates | G24: 0 | H24: 80 | I24: 0 | K24: 0 | L24: 80 | M24: 0 | N24: 0 | O24: 0 | P24: 542 | Q24: 0 | R24: 0 | S24: 0 | T24: =50+90 -> 140 | U24: 0 | V24: 50 | W24: 0 | X24: 0 | Y24: 0
A25: Management Commission 15% ( Inc V A T ) | B25: =0.1501*B14 -> 109.573 | C25: =0.1501*C14 -> 0 | D25: =0.1501*D14 -> 157.605 | E25: =0.1501*E14 -> 0 | F25: =0.1501*F14 -> 129.086 | G25: =0.1501*G14 -> 0 | H25: =0.1501*H14 -> 82.555 | I25: 0 | J25: =0.1501*J14 -> 160.1567 | K25: =0.1501*K14 -> 0 | L25: =0.1501*L14 -> 153.102 | M25: =0.1501*M14 -> 0 | N25: =0.1501*N14 -> 106.2708 | O25: =0.1501*O14 -> 0 | P25: =0.1501*P14 -> 97.565 | Q25: =0.1501*Q14 -> 0 | ... Y25: =0.1501*Y14 -> 0
A27: Total Expenditure | B27: =SUM(B19:B26) -> 739.683 | C27: =SUM(C19:C26) -> 0 | D27: =SUM(D19:D26) -> 850.605 | E27: =SUM(E19:E26) -> 0 | F27: =SUM(F19:F26) -> 588.086 | G27: =SUM(G19:G26) -> 0 | H27: =SUM(H19:H26) -> 1528.555 | I27: =SUM(I19:I26) -> 0 | ... Y27: =SUM(Y19:Y26) -> 0
A29: Balance c/f | B29: =B16-B27 -> 5.317 | C29: =C16-C27 -> 0 | D29: =D16-D27 -> 204.712 | E29: =E16-E27 -> 0 | F29: =F16-F27 -> 476.626 | G29: =G16-G27 -> 0 | H29: =H16-H27 -> -501.929 | I29: =I16-I27 -> 0 | ... Y29: =Y16-Y27 -> 0
A31: CONSOLIDATED INCOME & EXPENDITURE FOR THE 12 MONTHS
A33: INCOME | B33: USD | C33: ZIG
A34: Balance b/forward | B34: =B13 -> 15 | C34: =C13 -> 0
A35: Levies | B35: =B14+D14+F14+H14+J14+L14+N14+P14+R14+T14+V14+X14 -> 10650.52 | C35: 0
A36: TOTAL | B36: =SUM(B34:B35) -> 10665.52 | C36: =SUM(C34:C35) -> 0
A38: EXPENDITURE
A39: Repairs and maintanance | B39: =B19+D19+F19+H19+J19+L19+N19+P19+R19+T19+V19+X19 -> 1395 | C39: 0
A40: Electricity | B40: =B20+D20+F20+H20+J20+L20+N20+P20+R20+T20+V20+X20 -> 560 | C40: 0
A41: Utilities | B41: =B21+D21+F21+H21+J21+L21+N21+P21+R21+T21+V21+X21 -> 126.2
A42: Salaries | B42: =B22+D22+F22+H22+J22+L22+N22+P22+R22+T22+V22+X22 -> 5920.11 | C42: 0
A43: Security | B43: =B23+D23+F23+H23+J23+L23+N23+P23+R23+T23+V23+X23 -> 90
A44: Upper Manyame | B44: =B24+D24+F24+H24+J24+L24+N24+P24+R24+T24+V24+X24 -> 892
A45: Management Commission 15% ( Inc V A T ) | B45: =B25+D25+F25+H25+J25+L25+N25+P25+R25+T25+V25+X25 -> 1598.6431 | C45: 0
B46: =SUM(B39:B45) -> 10581.953 | C46: =SUM(C38:C45) -> 0
A48: Balance C/F | B48: =B36-B46 -> 83.566948 | C48: =C36-C46 -> 0
A52: INCOME SUMMARY 31/12/25
A54: ACCOUNT HOLDER | B54: Balance B/F | C54: Charge | D54: Amount Due | E54: Amount Paid | F54: Penalty | G54: Carried Forward
A55: Trevor Jasi 1 Sunset Villas | B55: 0 | C55: 50 | D55: =B55+C55 -> 50 | E55: 115 | F55: 0 | G55: =D55-E55+F55 -> -65
A56: Jane Midzi 2 Sunset Villas | B56: -50 | C56: 50 | D56: =B56+C56 -> 0 | E56: 0 | G56: =D56-E56+F56 -> 0
A57: Monica Muyengwa 3 Sunset Villas | B57: 0 | C57: 50 | D57: =B57+C57 -> 50 | E57: 50 | F57: 0 | G57: =D57-E57+F57 -> 0
A58: Bezel Mawere 4 Sunset Villas | B58: 20 | C58: 50 | D58: =B58+C58 -> 70 | E58: 50 | F58: 0 | G58: =D58-E58+F58 -> 20
A59: Jimmy Marowa 5 Sunset Villas | B59: 50 | C59: 50 | D59: =B59+C59 -> 100 | E59: 150 | F59: 0 | G59: =D59-E59+F59 -> -50
A60: Wendy Madzura 6 Sunset Villas | B60: 160 | C60: 50 | D60: =B60+C60 -> 210 | E60: 210 | F60: 0 | G60: =D60-E60+F60 -> 0
A61: Trymore Pandi 7 Sunset Villas | B61: -50 | C61: 50 | D61: =B61+C61 -> 0 | E61: 0 | F61: 0 | G61: =D61-E61+F61 -> 0
A62: Florine Ngarava 8 Sunset Villas | B62: 50 | C62: 50 | D62: =B62+C62 -> 100 | E62: 0 | F62: 0 | G62: =D62-E62+F62 -> 100
A63: Nobukosi Tshuma 9 Sunset Villas | B63: 100 | C63: 50 | D63: =B63+C63 -> 150 | E63: 0 | F63: 0 | G63: =D63-E63+F63 -> 150
A64: Pretty Jani 10 Sunset Villas | B64: 0 | C64: 50 | D64: =B64+C64 -> 50 | E64: 115 | F64: 0 | G64: =D64-E64+F64 -> -65
A65: Madeline Bera 11 Sunset Villas | B65: 80 | C65: 50 | D65: =B65+C65 -> 130 | E65: 160.52 | F65: 0 | G65: =D65-E65+F65 -> -30.52
A66: Chevelle Nandi 12 Sunset Villas | B66: 50 | C66: 50 | D66: =B66+C66 -> 100 | E66: 150 | F66: 0 | G66: =D66-E66+F66 -> -50
A67: Ashleigh Mwanza 13 Sunset Villas | B67: -50 | C67: 50 | D67: =B67+C67 -> 0 | E67: 65 | F67: 0 | G67: =D67-E67+F67 -> -65
A68: Yvonne Takavada 14 Sunset Villas | B68: -50 | C68: 50 | D68: =B68+C68 -> 0 | E68: 0 | F68: 0 | G68: =D68-E68+F68 -> 0
... A70: Robson Gweta 16 Sunset Villas | B70: 0 | C70: 50 | D70: =B70+C70 -> 50 | E70: 115 | F70: 0 | G70: =D70-E70+F70 -> -65
A71: Brian Bonda 17 Sunset Villas | B71: -50 | C71: 50 | D71: =B71+C71 -> 0 | E71: 0 | G71: =D71-E71+F71 -> 0
A72: Total | B72: =SUM(B55:B71) -> 210 | C72: =SUM(C55:C71) -> 850 | D72: =SUM(D55:D71) -> 1060 | E72: =SUM(E55:E71) -> 1245.52 | F72: =SUM(F55:F71) -> 0 | G72: =SUM(G55:G71) -> -185.52
A76: WORKING CAPITAL AS AT 31/12/25
B77: USD | C77: ZIG
A78: Debtors and Cash balances
A79: Cash balances | B79: =B48 -> 83.566948 | C79: =C29 -> 0
A80: Levies in arrears | B80: =SUMIF(G55:G71,">0") -> 270 | C80: 0
B81: =SUM(B79:B80) -> 353.56695 | C81: =SUM(C79:C80) -> 0
A83: Creditors
A84: Overdraft | B84: =B48*-1 -> -83.566948 | C84: 0
A85: Prepayments in levies | B85: =SUMIF(G55:G71,"<0")*-1 -> 455.52 | C85: 0
B86: =SUM(B84:B85) -> 371.95305 | C86: =SUM(C84:C85) -> 0
A88: Net Working Capital | B88: =B81-B86 -> -18.386104 | C88: =C81-C86 -> 0

Sheet Income & exp 12 months new  (2)
A1: Note that the logic for deriving income remains the same, that is the totals on the credit side of our landlord account. The path followed in this Income & Expenditure report is ='LANDLORD ACC DETAILED VIEW-LEVY'!G98
A2: This Income & Expenditure report derives its levy income from a landlord account with distorted credit side totals.
A4: Now that the wrong receipt and corrections have distorted our credit side totals, which now leads to differences in balances between our Income & Expenditure report and the Landlord Statement.
A5: The Income & Expenditure report now show a balance of $289 while the landlord statement has maintained its balance of $84.
A6: This discrepancy needs attention
A8: The way out of this problem is to adjust the credit side totals by removing the $210 of a wrong receipt and a $32 posted to cancel off commission deduction that was charged as a result of the wrong receipt.
A9: By doing so, the Income & Expenditure Report & Landlord Statement balances will tally .
A11: The next document A4 will clearly illustrate and provide a comprehensive solution to that problem.
A13: For now, let's fully understand this problem
A15: NEW APPROACH DERIVING LEVY INCOME FROM A COMPROMISED SOURCE
A17: SUNSET VILLAS
A18: INCOME AND EXPENDITURE FOR THE PERIOD ENDING 31 DEC 2025
A21: INCOME | B21: January | D21: February | F21: March | H21: April | J21: May | L21: June | N21: July | P21: August | R21: September | T21: October | V21: November | X21: December
B22: USD | C22: ZWG | D22: USD | E22: ZWG | F22: USD | G22: ZWG | H22: USD | I22: ZWG | J22: USD | K22: ZWG | L22: USD | M22: ZWG | N22: USD | O22: ZWG | P22: USD | Q22: ZWG | R22: USD | S22: ZWG | T22: USD | U22: ZWG | V22: USD | W22: ZWG | X22: USD | Y22: ZWG
A23: Balance b/forward | B23: 15 | C23: 0 | D23: =B39 -> 5.317 | E23: =C39 -> 0 | F23: =D39 -> 204.712 | G23: =E39 -> 0 | H23: =F39 -> 476.626 | I23: =G39 -> 0 | J23: =H39 -> -501.929 | K23: =I39 -> 0 | ... Y23: =W39 -> 0
A24: Levies | B24: =January!E42 -> 730 | C24: =JUNE!N11 -> 0 | D24: =FEB!E41 -> 1050 | E24: =FEB!M11 -> 0 | F24: ='MARCH 25'!E47 -> 860 | G24: =E40 -> 0 | H24: ='April 25'!E38 -> 550 | I24: 0 | J24: ='May25'!E46 -> 1067 | K24: ='May25'!N11 -> 0 | L24: =june25!E50 -> 1020 | M24: 0 | N24: ='july 25'!E44 -> 708 | O24: 0 | P24: =August25!E36 -> 650 | Q24: 0 | R24: =Sept!E44 -> 750 | S24: =Sept!N11 -> 0 | T24: =October25!E67 -> 1470 | U24: 0 | V24: ='NOV 25'!E31 -> 550 | W24: 0 | X24: ='LANDLORD ACC DETAILED VIEW-LEVY'!G98 -> 1487.52 | Y24: 0
A26: Amount before Expenditure | B26: =SUM(B23:B25) -> 745 | C26: =SUM(C23:C25) -> 0 | D26: =SUM(D23:D25) -> 1055.317 | E26: =SUM(E23:E25) -> 0 | F26: =SUM(F23:F25) -> 1064.712 | G26: =SUM(G23:G25) -> 0 | H26: =SUM(H23:H25) -> 1026.626 | I26: =SUM(I23:I25) -> 0 | ... Y26: =SUM(Y23:Y25) -> 0
A28: EXPENDITURE
A29: Repairs and maintanance | B29: =50+80 -> 130 | C29: 0 | D29: 0 | E29: 0 | F29: =30+140+276 -> 446 | G29: 0 | H29: 275 | I29: 0 | J29: =45+15+58 -> 118 | K29: 0 | L29: =58+20 -> 78 | M29: 0 | N29: =63+67 -> 130 | O29: 0 | P29: 0 | Q29: 0 | R29: 0 | S29: 0 | T29: =138+20 -> 158 | U29: 0 | V29: 60 | W29: 0 | X29: 0 | Y29: 0
A30: Electricity | B30: 0 | C30: 0 | D30: 150 | E30: 0 | G30: 0 | I30: 0 | K30: 0 | L30: 200 | M30: 0 | N30: 0 | O30: 0 | P30: 0 | Q30: 0 | R30: 10 | S30: 0 | T30: 0 | U30: 0 | V30: 200 | W30: 0 | X30: 0 | Y30: 0
A31: Utilities | B31: 10 | C31: 0 | D31: 0 | E31: 0 | F31: 13 | G31: 0 | H31: 5 | I31: 0 | K31: 0 | M31: 0 | N31: 0 | O31: 0 | P31: 0 | Q31: 0 | R31: 0 | S31: 0 | T31: 2.7 | U31: 0 | V31: 0 | W31: 0 | X31: 95.5 | Y31: 0
A32: Salaries | B32: =456+34.11 -> 490.11 | C32: 0 | D32: 543 | E32: 0 | G32: 0 | H32: =543+543 -> 1086 | I32: 0 | J32: 543 | K32: 0 | L32: 543 | M32: 0 | N32: 543 | O32: 0 | P32: 0 | Q32: 0 | R32: 543 | S32: 0 | T32: 543 | U32: 0 | V32: 543 | W32: 0 | X32: 543 | Y32: 0
A33: Security | R33: 90 | S33: 0 | T33: 0 | U33: 0 | V33: 0 | W33: 0 | X33: 0 | Y33: 0
A34: Upper Manyame rates | G34: 0 | H34: 80 | I34: 0 | K34: 0 | L34: 80 | M34: 0 | N34: 0 | O34: 0 | P34: 542 | Q34: 0 | R34: 0 | S34: 0 | T34: =50+90 -> 140 | U34: 0 | V34: 50 | W34: 0 | X34: 0 | Y34: 0
A35: Management Commission 15% ( Inc V A T ) | B35: =0.1501*B24 -> 109.573 | C35: =0.1501*C24 -> 0 | D35: =0.1501*D24 -> 157.605 | E35: =0.1501*E24 -> 0 | F35: =0.1501*F24 -> 129.086 | G35: =0.1501*G24 -> 0 | H35: =0.1501*H24 -> 82.555 | I35: 0 | J35: =0.1501*J24 -> 160.1567 | K35: =0.1501*K24 -> 0 | L35: =0.1501*L24 -> 153.102 | M35: =0.1501*M24 -> 0 | N35: =0.1501*N24 -> 106.2708 | O35: =0.1501*O24 -> 0 | P35: =0.1501*P24 -> 97.565 | Q35: =0.1501*Q24 -> 0 | ... Y35: =0.1501*Y24 -> 0
A37: Total Expenditure | B37: =SUM(B29:B36) -> 739.683 | C37: =SUM(C29:C36) -> 0 | D37: =SUM(D29:D36) -> 850.605 | E37: =SUM(E29:E36) -> 0 | F37: =SUM(F29:F36) -> 588.086 | G37: =SUM(G29:G36) -> 0 | H37: =SUM(H29:H36) -> 1528.555 | I37: =SUM(I29:I36) -> 0 | ... Y37: =SUM(Y29:Y36) -> 0
A39: Balance c/f | B39: =B26-B37 -> 5.317 | C39: =C26-C37 -> 0 | D39: =D26-D37 -> 204.712 | E39: =E26-E37 -> 0 | F39: =F26-F37 -> 476.626 | G39: =G26-G37 -> 0 | H39: =H26-H37 -> -501.929 | I39: =I26-I37 -> 0 | ... Y39: =Y26-Y37 -> 0
A41: CONSOLIDATED INCOME & EXPENDITURE FOR THE 12 MONTHS
A43: INCOME | B43: USD | C43: ZIG
A44: Balance b/forward | B44: =B23 -> 15 | C44: =C23 -> 0
A45: Levies | B45: =B24+D24+F24+H24+J24+L24+N24+P24+R24+T24+V24+X24 -> 10892.52 | C45: 0
A46: TOTAL | B46: =SUM(B44:B45) -> 10907.52 | C46: =SUM(C44:C45) -> 0
A48: EXPENDITURE
A49: Repairs and maintanance | B49: =B29+D29+F29+H29+J29+L29+N29+P29+R29+T29+V29+X29 -> 1395 | C49: 0
A50: Electricity | B50: =B30+D30+F30+H30+J30+L30+N30+P30+R30+T30+V30+X30 -> 560 | C50: 0
A51: Utilities | B51: =B31+D31+F31+H31+J31+L31+N31+P31+R31+T31+V31+X31 -> 126.2
A52: Salaries | B52: =B32+D32+F32+H32+J32+L32+N32+P32+R32+T32+V32+X32 -> 5920.11 | C52: 0
A53: Security | B53: =B33+D33+F33+H33+J33+L33+N33+P33+R33+T33+V33+X33 -> 90
A54: Upper Manyame | B54: =B34+D34+F34+H34+J34+L34+N34+P34+R34+T34+V34+X34 -> 892
A55: Management Commission 15% ( Inc V A T ) | B55: =B35+D35+F35+H35+J35+L35+N35+P35+R35+T35+V35+X35 -> 1634.9673 | C55: 0
B56: =SUM(B49:B55) -> 10618.277 | C56: =SUM(C48:C55) -> 0
A58: Balance C/F | B58: =B46-B56 -> 289.24275 | C58: =C46-C56 -> 0
A62: INCOME SUMMARY 31/12/25
A64: ACCOUNT HOLDER | B64: Balance B/F | C64: Charge | D64: Amount Due | E64: Amount Paid | F64: Penalty | G64: Carried Forward
A65: Trevor Jasi 1 Sunset Villas | B65: 0 | C65: 50 | D65: =B65+C65 -> 50 | E65: 115 | F65: 0 | G65: =D65-E65+F65 -> -65
A66: Jane Midzi 2 Sunset Villas | B66: -50 | C66: 50 | D66: =B66+C66 -> 0 | E66: 0 | G66: =D66-E66+F66 -> 0
A67: Monica Muyengwa 3 Sunset Villas | B67: 0 | C67: 50 | D67: =B67+C67 -> 50 | E67: 50 | F67: 0 | G67: =D67-E67+F67 -> 0
A68: Bezel Mawere 4 Sunset Villas | B68: 20 | C68: 50 | D68: =B68+C68 -> 70 | E68: 50 | F68: 0 | G68: =D68-E68+F68 -> 20
A69: Jimmy Marowa 5 Sunset Villas | B69: 50 | C69: 50 | D69: =B69+C69 -> 100 | E69: 150 | F69: 0 | G69: =D69-E69+F69 -> -50
A70: Wendy Madzura 6 Sunset Villas | B70: 160 | C70: 50 | D70: =B70+C70 -> 210 | E70: 210 | F70: 0 | G70: =D70-E70+F70 -> 0
A71: Trymore Pandi 7 Sunset Villas | B71: -50 | C71: 50 | D71: =B71+C71 -> 0 | E71: 0 | F71: 0 | G71: =D71-E71+F71 -> 0
A72: Florine Ngarava 8 Sunset Villas | B72: 50 | C72: 50 | D72: =B72+C72 -> 100 | E72: 0 | F72: 0 | G72: =D72-E72+F72 -> 100
A73: Nobukosi Tshuma 9 Sunset Villas | B73: 100 | C73: 50 | D73: =B73+C73 -> 150 | E73: 0 | F73: 0 | G73: =D73-E73+F73 -> 150
A74: Pretty Jani 10 Sunset Villas | B74: 0 | C74: 50 | D74: =B74+C74 -> 50 | E74: 115 | F74: 0 | G74: =D74-E74+F74 -> -65
A75: Madeline Bera 11 Sunset Villas | B75: 80 | C75: 50 | D75: =B75+C75 -> 130 | E75: 160.52 | F75: 0 | G75: =D75-E75+F75 -> -30.52
A76: Chevelle Nandi 12 Sunset Villas | B76: 50 | C76: 50 | D76: =B76+C76 -> 100 | E76: 150 | F76: 0 | G76: =D76-E76+F76 -> -50
A77: Ashleigh Mwanza 13 Sunset Villas | B77: -50 | C77: 50 | D77: =B77+C77 -> 0 | E77: 65 | F77: 0 | G77: =D77-E77+F77 -> -65
A78: Yvonne Takavada 14 Sunset Villas | B78: -50 | C78: 50 | D78: =B78+C78 -> 0 | E78: 0 | F78: 0 | G78: =D78-E78+F78 -> 0
... A80: Robson Gweta 16 Sunset Villas | B80: 0 | C80: 50 | D80: =B80+C80 -> 50 | E80: 115 | F80: 0 | G80: =D80-E80+F80 -> -65
A81: Brian Bonda 17 Sunset Villas | B81: -50 | C81: 50 | D81: =B81+C81 -> 0 | E81: 0 | G81: =D81-E81+F81 -> 0
A82: Total | B82: =SUM(B65:B81) -> 210 | C82: =SUM(C65:C81) -> 850 | D82: =SUM(D65:D81) -> 1060 | E82: =SUM(E65:E81) -> 1245.52 | F82: =SUM(F65:F81) -> 0 | G82: =SUM(G65:G81) -> -185.52
A86: WORKING CAPITAL AS AT 31/12/25
B87: USD | C87: ZIG
A88: Debtors and Cash balances
A89: Cash balances | B89: =B58 -> 289.24275 | C89: =C39 -> 0
A90: Levies in arrears | B90: =SUMIF(G65:G81,">0") -> 270 | C90: 0
B91: =SUM(B89:B90) -> 559.24275 | C91: =SUM(C89:C90) -> 0
A93: Creditors
A94: Overdraft | B94: =B58*-1 -> -289.24275 | C94: 0
A95: Prepayments in levies | B95: =SUMIF(G65:G81,"<0")*-1 -> 455.52 | C95: 0
B96: =SUM(B94:B95) -> 166.27725 | C96: =SUM(C94:C95) -> 0
A98: Net Working Capital | B98: =B91-B96 -> 392.9655 | C98: =C91-C96 -> 0

Sheet LANDLORD ACC DETAILED VIEW-LEVY
A2: Landlord: Sunset Villas Owners Association
A4: Account ID:53845/06
A5: Category : Levy
A6: Account Currency:USD
A7: Transaction Period:2025-12-01 - 2025-12-31
A9: Transaction ID | B9: Date | C9: Contra | D9: Ref | E9: Description | F9: Debit | G9: Credit | H9: Balance
E10: Balance brought forward | H10: -337
A11: 1452335 | B11: 45993 | C11: 6000/010 | D11: RCT-21345 | E11: Levy Payment -Ecocash USD-Robson Gweta 16 Sunset Leaseid-5833 Ref-LEVY- ECOCASH-27/11/25 | G11: 50 | H11: -288.63
A12: 1452338 | B12: 45993 | C12: 1000/010 | D12: CMA-19427 | E12: Levy Commission-Ecocash USD-Robson Gweta 16 Sunset Leaseid-5833 Ref-LEVY- ECOCASH-27/11/25 | F12: 7.51 | H12: -296.14
A13: 1453235 | B13: 45995 | C13: 6000/010 | D13: RCT-21348 | E13: Levy Payment-FBC Bank-Bezel Mawere 4 Sunset- Leaseid-5821 Ref-LEVY-TRANSFER-02/12/25 | G13: 50 | H13: -246.14
A14: 1453238 | B14: 45995 | C14: 1000/010 | D14: CMA-19437 | E14: Levy Commission--FBC Bank-Bezel Mawere 4 Sunset- Leaseid-5821 Ref-LEVY-TRANSFER-02/12/25 | F14: 7.51 | H14: -253.65
A15: 1453242 | B15: 45995 | C15: 6000/010 | D15: RCT-21367 | E15: Levy Payment-ZB Bank-Monica Muyengwa -3 Sunset Leaseid-5820 Ref-LEVY-TRANSFER-03/12/25 | G15: 50 | H15: -203.65
A16: 1453245 | B16: 45995 | C16: 1000/010 | D16: CMA-19442 | E16: Levy Commission-ZB Bank-Monica Muyengwa -3 Sunset Leaseid-5820 Ref-LEVY-TRANSFER-03/12/25 | F16: 7.51 | H16: -211.16
A17: 1453580 | B17: 45995 | C17: 6000/010 | D17: RCT-21369 | E17: Levy Payment -Ecocash USD- Pretty Jani-10 Sunset-Leaseid-5827 Ref-LEVY-PRETTY JANI-10 SUNSET-ECOCASH-02/12/25 | G17: 50 | H17: -161.16
A18: 1453583 | B18: 45995 | C18: 1000/010 | D18: CMA-19444 | E18: Levy Commission-Ecocash USD- Pretty Jani-10 Sunset-Leaseid-5827 Ref-LEVY-PRETTY JANI-10 SUNSET-ECOCASH-02/12/25 | F18: 7.51 | H18: -168.67
A19: 1453658 | B19: 45995 | C19: 6000/010 | D19: RCT-21377 | E19: Levy Payment-Cash USD-Madeline Bera 11 Sunset-Leaseid-5828 Ref-LEVY - 11 Sunset | G19: 95.52 | H19: -73.15
A20: 1453661 | B20: 45995 | C20: 1000/010 | D20: CMA-19447 | E20: Levy Commission-Cash USD-Madeline Bera 11 Sunset-Leaseid-5828 Ref-LEVY - 11 Sunset | F20: 14.34 | H20: -87.49
A21: 1456340 | B21: 45995 | C21: 2000/002 | D21: P3143 | E21: PURCHASE OF SOLAR LIGHTS | F21: 95.52 | H21: -183.01
A22: 1455657 | B22: 46000 | C22: 6000/010 | D22: RCT-21379 | E22: Levy Payment -Stanbic Bank-Trevor Jasi-1 Sunset-Leaseid-5817 Ref-LEVY-1 SUNSET-TRANSFER-05/12/25 | G22: 50 | H22: -133.01
A23: 1455660 | B23: 46000 | C23: 1000/010 | D23: CMA-19467 | E23: Levy Commission-Stanbic Bank-Trevor Jasi-1 Sunset-Leaseid-5817 Ref-LEVY-1 SUNSET-TRANSFER-05/12/25 | F23: 7.51 | H23: -140.52
A24: 1457914 | B24: 46007 | C24: 6000/010 | D24: RCT-21381 | E24: Levy Payment-Cash USD- Wendy Madzura 6 Sunset Leaseid-5823 Ref-LEVY - 6 SUNSET VILLAS | G24: 210 | H24: 69.48
A25: 1457917 | B25: 46007 | C25: 1000/010 | D25: CMA-19475 | E25: Levy Commission-Cash USD- Wendy Madzura 6 Sunset Leaseid-5823 Ref-LEVY - 6 SUNSET VILLAS | F25: 31.52 | H25: 37.96
A26: 1458555 | B26: 46009 | C26: 6000/010 | D26: RCT-21383 | E26: Levy Payment-Ecocash USD-Chevelle Nandi 12 Sunset-Leaseid-5829 Ref-LEVY-CHEVELLE NANDI-12 SUNSET-ECOCASH-17/12/25 | G26: 150 | H26: 187.96
A27: 1458558 | B27: 46009 | C27: 1000/010 | D27: CMA-19480 | E27: Levy Commission -Ecocash USD-Chevelle Nandi 12 Sunset-Leaseid-5829 Ref-LEVY-CHEVELLE NANDI-12 SUNSET-ECOCASH-17/12/25 | F27: 22.52 | H27: 165.44
A28: 1458797 | B28: 46010 | C28: 2000/004 | D28: P3198 | E28: Journal ref-STAFF SALARIES | F28: 543 | H28: -377.56
A29: 1459776 | B29: 46015 | C29: 6000/010 | D29: RCT-21385 | E29: Levy Payment -Stanbic Bank-Trevor Jasi-1 Sunset-Leaseid-5817 Ref-LEVY-1 SUNSET-TRANSFER | G29: 65 | H29: -312.56
A30: 1459779 | B30: 46015 | C30: 1000/010 | D30: CMA-19481 | E30: Levy Commission-Stanbic Bank-Trevor Jasi-1 Sunset-Leaseid-5817 Ref-LEVY-1 SUNSET-TRANSFER | F30: 9.75 | H30: -322.31
A31: 1459944 | B31: 46020 | C31: 6000/010 | D31: RCT-21386 | E31: Levy Payment-Cash USD- Asheigh Mwanza 13 SunsetLeaseid-5830 Ref-LEVY 13 SUNSET MWANZA CASH | G31: 65 | H31: -257.31
A32: 1459947 | B32: 46020 | C32: 1000/010 | D32: CMA-19482 | E32: Levy Commission-Cash USD- Asheigh Mwanza 13 SunsetLeaseid-5830 Ref-LEVY 13 SUNSET MWANZA CASH | F32: 9.75 | H32: -267.06
A33: 1459951 | B33: 46020 | C33: 6000/010 | D33: RCT-21390 | E33: Levy Payment-Cash USD-Pretty Jani 10 Sunset- Leaseid-5827 Ref-LEVY 10 SUNSET JANI CASH | G33: 65 | H33: -202.06
A34: 1459954 | B34: 46020 | C34: 1000/010 | D34: CMA-19484 | E34: Levy Commission-Cash USD-Pretty Jani 10 Sunset- Leaseid-5827 Ref-LEVY 10 SUNSET JANI CASH | F34: 9.75 | H34: -211.81
A35: 1460016 | B35: 46020 | C35: 6000/010 | D35: RCT-21392 | E35: Levy Payment -Ecocash USD-Jimmy Marowa 5 Sunset Leaseid-5822 Ref-LEVY-Jimmy Marowa-5 Sunset-ECOCASH-23/12/25 | G35: 150 | H35: -61.81
A36: 1460019 | B36: 46020 | C36: 1000/010 | D36: CMA-19489 | E36: Levy Commission Ecocash USD-Jimmy Marowa 5 Sunset Leaseid-5822Ref-LEVY-Jimmy Marowa-5 Sunset-ECOCASH-23/12/25 | F36: 22.52 | H36: -84.33
A37: 1460034 | B37: 46020 | C37: 6000/010 | D37: RCT-21394 | E37: Payment-Ecocash USD-Robson Gweta 16 Sunset Leaseid-5833 Ref-LEVY-PARADZA E-16 Sunset-ECOCASH-28/12/25 | G37: 65 | H37: -19.33
A38: 1460037 | B38: 46020 | C38: 1000/010 | D38: CMA-19491 | E38: Levy Commission -Ecocash USD-Robson Gweta 16 Sunset Leaseid-5833 Ref-LEVY-PARADZA E-16 Sunset-ECOCASH-28/12/25 | F38: 9.75 | H38: -29.08
A39: 1460050 | B39: 46021 | C39: 6000/010 | D39: RCT-21395 | E39: Levy Payment -Ecocash USD-Madeine Bera 11 SunsetLeaseid-5828 Ref-LEVY-15 Sunset-ECOCASH-29/12/25 | G39: 65 | H39: 35.92
A40: 1460053 | B40: 46021 | C40: 1000/010 | D40: CMA-19493 | E40: Levy Commission-Ecocash USD-Madeine Bera 11 SunsetLeaseid-5828 Ref-LEVY-15 Sunset-ECOCASH-29/12/25 | F40: 9.75 | H40: 26.17
A41: 1461811 | B41: 46022 | C41: 6000/010 | D41: RCT-21399 | E41: Levy Payment-Ecocash USD- Jessie Mugoni 15 SUNSET Leaseid-5832Ref-LEVY-ECOCASH-31/12/25 | G41: 65 | H41: 91.17
A42: 1461814 | B42: 46022 | C42: 1000/010 | D42: CMA-19495 | E42: Levy Commission Leaseid-5832 Ref-LEVY-15 SUNSET-ECOCASH-31/12/25 | F42: 9.79 | H42: 81.38
F43: 825.51 | G43: 1245.52 | H43: 84
A46: The landlord statement below is still the same, opening balances, receipts and expenditure are the same except that this one has a scenario which is encountered quite a number of times in several properties we manage.
A48: In this example,Wendy Madzura's payment was recorded twice mistakenly but it was reversed immediately through journals so as to keep the balances correct.
A49: The total on the debit side increased from $826 to $1068 because of the $210 posted to cancel off the second receipt of $210 and a $32 commission that was initially deducted from the wrong receipt.
A50: The credit side balance increased as well from $1246 to $1488; due to the $210 wrong receipt in row 77 and a $32 commission reversal in row $80.
A53: Landlord: Sunset Villas Owners Association
A55: Account ID:53845/06
A56: Category : Levy
A57: Account Currency:USD
A58: Transaction Period:2025-12-01 - 2025-12-31
A60: Transaction ID | B60: Date | C60: Contra | D60: Ref | E60: Description | F60: Debit | G60: Credit | H60: Balance
E61: Balance brought forward | H61: -337
A62: 1452335 | B62: 45993 | C62: 6000/010 | D62: RCT-21345 | E62: Levy Payment -Ecocash USD-Robson Gweta 16 Sunset Leaseid-5833 Ref-LEVY- ECOCASH-27/11/25 | G62: 50 | H62: =H61-F62+G62 -> -287
A63: 1452338 | B63: 45993 | C63: 1000/010 | D63: CMA-19427 | E63: Levy Commission-Ecocash USD-Robson Gweta 16 Sunset Leaseid-5833 Ref-LEVY- ECOCASH-27/11/25 | F63: 7.51 | H63: =H62-F63+G63 -> -294.51
A64: 1453235 | B64: 45995 | C64: 6000/010 | D64: RCT-21348 | E64: Levy Payment-FBC Bank-Bezel Mawere 4 Sunset- Leaseid-5821 Ref-LEVY-TRANSFER-02/12/25 | G64: 50 | H64: =H63-F64+G64 -> -244.51
A65: 1453238 | B65: 45995 | C65: 1000/010 | D65: CMA-19437 | E65: Levy Commission--FBC Bank-Bezel Mawere 4 Sunset- Leaseid-5821 Ref-LEVY-TRANSFER-02/12/25 | F65: 7.51 | H65: =H64-F65+G65 -> -252.02
A66: 1453242 | B66: 45995 | C66: 6000/010 | D66: RCT-21367 | E66: Levy Payment-ZB Bank-Monica Muyengwa -3 Sunset Leaseid-5820 Ref-LEVY-TRANSFER-03/12/25 | G66: 50 | H66: =H65-F66+G66 -> -202.02
A67: 1453245 | B67: 45995 | C67: 1000/010 | D67: CMA-19442 | E67: Levy Commission-ZB Bank-Monica Muyengwa -3 Sunset Leaseid-5820 Ref-LEVY-TRANSFER-03/12/25 | F67: 7.51 | H67: =H66-F67+G67 -> -209.53
A68: 1453580 | B68: 45995 | C68: 6000/010 | D68: RCT-21369 | E68: Levy Payment -Ecocash USD- Pretty Jani-10 Sunset-Leaseid-5827 Ref-LEVY-PRETTY JANI-10 SUNSET-ECOCASH-02/12/25 | G68: 50 | H68: =H67-F68+G68 -> -159.53
A69: 1453583 | B69: 45995 | C69: 1000/010 | D69: CMA-19444 | E69: Levy Commission-Ecocash USD- Pretty Jani-10 Sunset-Leaseid-5827 Ref-LEVY-PRETTY JANI-10 SUNSET-ECOCASH-02/12/25 | F69: 7.51 | H69: =H68-F69+G69 -> -167.04
A70: 1453658 | B70: 45995 | C70: 6000/010 | D70: RCT-21377 | E70: Levy Payment-Cash USD-Madeline Bera 11 Sunset-Leaseid-5828 Ref-LEVY - 11 Sunset | G70: 95.52 | H70: =H69-F70+G70 -> -71.52
A71: 1453661 | B71: 45995 | C71: 1000/010 | D71: CMA-19447 | E71: Levy Commission-Cash USD-Madeline Bera 11 Sunset-Leaseid-5828 Ref-LEVY - 11 Sunset | F71: 14.34 | H71: =H70-F71+G71 -> -85.86
A72: 1456340 | B72: 45995 | C72: 2000/002 | D72: P3143 | E72: PURCHASE OF SOLAR LIGHTS | F72: 95.52 | H72: =H71-F72+G72 -> -181.38
A73: 1455657 | B73: 46000 | C73: 6000/010 | D73: RCT-21379 | E73: Levy Payment -Stanbic Bank-Trevor Jasi-1 Sunset-Leaseid-5817 Ref-LEVY-1 SUNSET-TRANSFER-05/12/25 | G73: 50 | H73: =H72-F73+G73 -> -131.38
A74: 1455660 | B74: 46000 | C74: 1000/010 | D74: CMA-19467 | E74: Levy Commission-Stanbic Bank-Trevor Jasi-1 Sunset-Leaseid-5817 Ref-LEVY-1 SUNSET-TRANSFER-05/12/25 | F74: 7.51 | H74: =H73-F74+G74 -> -138.89
A75: 1457914 | B75: 46007 | C75: 6000/010 | D75: RCT-21381 | E75: Levy Payment-Cash USD- Wendy Madzura 6 Sunset Leaseid-5823 Ref-LEVY - 6 SUNSET VILLAS | G75: 210 | H75: =H74-F75+G75 -> 71.11
A76: 1457917 | B76: 46007 | C76: 1000/010 | D76: CMA-19475 | E76: Levy Commission-Cash USD- Wendy Madzura 6 Sunset Leaseid-5823 Ref-LEVY - 6 SUNSET VILLAS | F76: 31.52 | H76: =H75-F76+G76 -> 39.59
A77: 1457918 | B77: 46007 | C77: 6000/010 | D77: RCT-21382 | E77: Levy Payment-Cash USD- Wendy Madzura 6 Sunset Leaseid-5823 Ref-LEVY - 6 SUNSET VILLAS | G77: 210 | H77: =H76-F77+G77 -> 249.59
A78: 1457919 | B78: 46007 | C78: 1000/010 | D78: CMA-19476 | E78: Levy Commission-Cash USD- Wendy Madzura 6 Sunset Leaseid-5823 Ref-LEVY - 6 SUNSET VILLAS | F78: 32 | H78: =H77-F78+G78 -> 217.59
A79: 1457925 | B79: 46007 | D79: RCT-21382 | E79: Mispost reversed-Levy Payment-Cash USD- Wendy Madzura 6 Sunset Leaseid-5823 Ref-LEVY - 6 SUNSET VILLAS | F79: 210 | H79: =H78-F79+G79 -> 7.59
A80: 1457926 | B80: 46007 | D80: CMA-19476 | E80: Mispost reversed-Levy Commission-Cash USD- Wendy Madzura 6 Sunset Leaseid-5823 Ref-LEVY - 6 SUNSET VILLAS | G80: 32 | H80: =H79-F80+G80 -> 39.59
A81: 1458555 | B81: 46009 | C81: 6000/010 | D81: RCT-21383 | E81: Levy Payment-Ecocash USD-Chevelle Nandi 12 Sunset-Leaseid-5829 Ref-LEVY-CHEVELLE NANDI-12 SUNSET-ECOCASH-17/12/25 | G81: 150 | H81: =H80-F81+G81 -> 189.59
A82: 1458558 | B82: 46009 | C82: 1000/010 | D82: CMA-19480 | E82: Levy Commission -Ecocash USD-Chevelle Nandi 12 Sunset-Leaseid-5829 Ref-LEVY-CHEVELLE NANDI-12 SUNSET-ECOCASH-17/12/25 | F82: 22.52 | H82: =H81-F82+G82 -> 167.07
A83: 1458797 | B83: 46010 | C83: 2000/004 | D83: P3198 | E83: Journal ref-STAFF SALARIES | F83: 543 | H83: =H82-F83+G83 -> -375.93
A84: 1459776 | B84: 46015 | C84: 6000/010 | D84: RCT-21385 | E84: Levy Payment -Stanbic Bank-Trevor Jasi-1 Sunset-Leaseid-5817 Ref-LEVY-1 SUNSET-TRANSFER | G84: 65 | H84: =H83-F84+G84 -> -310.93
A85: 1459779 | B85: 46015 | C85: 1000/010 | D85: CMA-19481 | E85: Levy Commission-Stanbic Bank-Trevor Jasi-1 Sunset-Leaseid-5817 Ref-LEVY-1 SUNSET-TRANSFER | F85: 9.75 | H85: =H84-F85+G85 -> -320.68
A86: 1459944 | B86: 46020 | C86: 6000/010 | D86: RCT-21386 | E86: Levy Payment-Cash USD- Asheigh Mwanza 13 SunsetLeaseid-5830 Ref-LEVY 13 SUNSET MWANZA CASH | G86: 65 | H86: =H85-F86+G86 -> -255.68
A87: 1459947 | B87: 46020 | C87: 1000/010 | D87: CMA-19482 | E87: Levy Commission-Cash USD- Asheigh Mwanza 13 SunsetLeaseid-5830 Ref-LEVY 13 SUNSET MWANZA CASH | F87: 9.75 | H87: =H86-F87+G87 -> -265.43
A88: 1459951 | B88: 46020 | C88: 6000/010 | D88: RCT-21390 | E88: Levy Payment-Cash USD-Pretty Jani 10 Sunset- Leaseid-5827 Ref-LEVY 10 SUNSET JANI CASH | G88: 65 | H88: =H87-F88+G88 -> -200.43
A89: 1459954 | B89: 46020 | C89: 1000/010 | D89: CMA-19484 | E89: Levy Commission-Cash USD-Pretty Jani 10 Sunset- Leaseid-5827 Ref-LEVY 10 SUNSET JANI CASH | F89: 9.75 | H89: =H88-F89+G89 -> -210.18
A90: 1460016 | B90: 46020 | C90: 6000/010 | D90: RCT-21392 | E90: Levy Payment -Ecocash USD-Jimmy Marowa 5 Sunset Leaseid-5822 Ref-LEVY-Jimmy Marowa-5 Sunset-ECOCASH-23/12/25 | G90: 150 | H90: =H89-F90+G90 -> -60.18
A91: 1460019 | B91: 46020 | C91: 1000/010 | D91: CMA-19489 | E91: Levy Commission Ecocash USD-Jimmy Marowa 5 Sunset Leaseid-5822Ref-LEVY-Jimmy Marowa-5 Sunset-ECOCASH-23/12/25 | F91: 22.52 | H91: =H90-F91+G91 -> -82.7
A92: 1460034 | B92: 46020 | C92: 6000/010 | D92: RCT-21394 | E92: Payment-Ecocash USD-Robson Gweta 16 Sunset Leaseid-5833 Ref-LEVY-PARADZA E-16 Sunset-ECOCASH-28/12/25 | G92: 65 | H92: =H91-F92+G92 -> -17.7
A93: 1460037 | B93: 46020 | C93: 1000/010 | D93: CMA-19491 | E93: Levy Commission -Ecocash USD-Robson Gweta 16 Sunset Leaseid-5833 Ref-LEVY-PARADZA E-16 Sunset-ECOCASH-28/12/25 | F93: 9.75 | H93: =H92-F93+G93 -> -27.45
A94: 1460050 | B94: 46021 | C94: 6000/010 | D94: RCT-21395 | E94: Levy Payment -Ecocash USD-Madeine Bera 11 SunsetLeaseid-5828 Ref-LEVY-15 Sunset-ECOCASH-29/12/25 | G94: 65 | H94: =H93-F94+G94 -> 37.55
A95: 1460053 | B95: 46021 | C95: 1000/010 | D95: CMA-19493 | E95: Levy Commission-Ecocash USD-Madeine Bera 11 SunsetLeaseid-5828 Ref-LEVY-15 Sunset-ECOCASH-29/12/25 | F95: 9.75 | H95: =H94-F95+G95 -> 27.8
A96: 1461811 | B96: 46022 | C96: 6000/010 | D96: RCT-21399 | E96: Levy Payment-Ecocash USD- Jessie Mugoni 15 SUNSET Leaseid-5832Ref-LEVY-ECOCASH-31/12/25 | G96: 65 | H96: =H95-F96+G96 -> 92.8
A97: 1461814 | B97: 46022 | C97: 1000/010 | D97: CMA-19495 | E97: Levy Commission Leaseid-5832 Ref-LEVY-15 SUNSET-ECOCASH-31/12/25 | F97: 9.79 | H97: =H96-F97+G97 -> 83.01
F98: =SUM(F61:F97) -> 1067.51 | G98: =SUM(G61:G97) -> 1487.52 | H98: 84
A99: The aim of the reversal of $210 receipt is to keep our landlord statement balance correct, but it leads to a huge distortion on our credit-side totals, which our primary source of our income.
A100: The landlord statement is correct in accounting standards , as it keeps the landlorlord liabilty correct, without risking paying out more money to the landlord, but for system development it poses a huge challenge.
A102: Let’s go to document A4 for a comprehensive solution.

Sheet NOV 25
A1: Statement | N1: Roll Over Summary
N2: landlord - Coronation Gardens Onwers Association
A3: Account Holder: Coronation Gardens Onwers Association | N3: Period: 2025-11-01 to 2025-11-30
N4: Currency: USD
A5: Account ID:58345
A6: Account Currency:USD
A7: Transaction Period:2025-11-01 - 2025-11-30
N8: Property - Coronation Gardens, Greendale, Harare
A9: ID | B9: Date | C9: Description | D9: Debit | E9: Credit | F9: Balance | N9: LeaseID | O9: Tenant | P9: Balance B/F | Q9: Amount Charged | R9: Amount Due | S9: Amount Paid | T9: Carried Forward
C10: Balance brought forward | F10: 46.96 | N10: 5817 | O10: Agnes Furidze 1 Coronation | P10: -50 | Q10: 50 | R10: 0 | S10: 0 | T10: 0
A11: 1444386 | B11: 45971 | C11: Payment Leaseid-5820 Kudzanayi Kachere 3 Coronation Ref-LEVY-KACHERE K-3 CORONATION-ECOCASH-08/11/25 | E11: 50 | F11: 96.96 | N11: 5819 | O11: Eva Mutangadura 2 Coronation | P11: -50 | Q11: 50 | R11: 0 | S11: 50 | T11: -50
A12: 1444389 | B12: 45971 | C12: Levy Commission Leaseid-5820 Ref-LEVY-KACHERE K-3 CORONATION-ECOCASH-08/11/25 | D12: 7.51 | F12: 89.45 | N12: 5820 | O12: Kudzanayi Kachere 3 Coronation | P12: 0 | Q12: 50 | R12: 50 | S12: 50 | T12: 0
A13: 1445542 | B13: 45973 | C13: Payment Leaseid-5825 Lody Machiwenyika 8 Coronation Ref-LEVY - 8 CORONATION/zesa | E13: 200 | F13: 289.45 | N13: 5821 | O13: Hebros Dubai 4 Coronation | P13: 20 | Q13: 50 | R13: 70 | S13: 50 | T13: 20
A14: 1445545 | B14: 45973 | C14: Levy Commission Leaseid-5825 Ref-LEVY - 8 CORONATION/zesa | D14: 30.02 | F14: 259.43 | N14: 5822 | O14: Tatenda Ngowe 5 Coronation | P14: 0 | Q14: 50 | R14: 50 | S14: 0 | T14: 50
A15: 1445788 | B15: 45973 | C15: Payment Ref-ZESA PURCHASE -JULY -OCTOBER 2025 | D15: 200 | F15: 59.43 | N15: 5823 | O15: Maud Silibaziso 6 Coronation | P15: 110 | Q15: 50 | R15: 160 | S15: 0 | T15: 160
A16: 1446048 | B16: 45974 | C16: Payment Leaseid-5821 Hebros Dubai 4 Coronation Ref-LEVY-DUBAI H-4 CORONATION-TRANSFER-10/11/25 | E16: 50 | F16: 109.43 | N16: 5824 | O16: Gibson Taruwinga 7 Coronation | P16: -50 | Q16: 50 | R16: 0 | S16: 50 | T16: -50
A17: 1446051 | B17: 45974 | C17: Levy Commission Leaseid-5821 Ref-LEVY-DUBAI H-4 CORONATION-TRANSFER-10/11/25 | D17: 7.51 | F17: 101.92 | N17: 5825 | O17: Lody Machiwenyika 8 Coronation | P17: 200 | Q17: 50 | R17: 250 | S17: 200 | T17: 50
A18: 1447653 | B18: 45980 | C18: Payment Ref-UPPER MANYAME | D18: 50 | F18: 51.92 | N18: 5826 | O18: Unit 9 Coronation Gardens | P18: 50 | Q18: 50 | R18: 100 | S18: 0 | T18: 100
A19: 1448865 | B19: 45988 | C19: Payment Leaseid-5830 Siketiwe Marima 13 Coronation Ref-LEVY - 13 CORONATION VILLAS | E19: 50 | F19: 101.92 | N19: 5827 | O19: Dorothy R. S Makoni 10 Coronation | P19: -50 | Q19: 50 | R19: 0 | S19: 0 | T19: 0
A20: 1448868 | B20: 45988 | C20: Levy Commission Leaseid-5830 Ref-LEVY - 13 CORONATION VILLAS | D20: 7.51 | F20: 94.41 | N20: 5828 | O20: Farai Chivaura 11 Coronation | P20: 30 | Q20: 50 | R20: 80 | S20: 0 | T20: 80
A21: 1448872 | B21: 45988 | C21: Payment Leaseid-5831 Phillers Gwengo 14 Coronation Ref-LEVY - 14 CORONATION VILLAS | E21: 50 | F21: 144.41 | N21: 5829 | O21: Rose Chanakira 12 Coronation | P21: 0 | Q21: 50 | R21: 50 | S21: 0 | T21: 50
A22: 1448875 | B22: 45988 | C22: Levy Commission Leaseid-5831 Ref-LEVY - 14 CORONATION VILLAS | D22: 7.51 | F22: 136.9 | N22: 5830 | O22: Siketiwe Marima 13 Coronation | P22: -50 | Q22: 50 | R22: 0 | S22: 50 | T22: -50
A23: 1448879 | B23: 45988 | C23: Payment Leaseid-5832 Toko Muodzi Ross 15 Coronation Gardens Ref-LEVY - 15 CORONATION VILLAS | E23: 50 | F23: 186.9 | N23: 5831 | O23: Phillers Gwengo 14 Coronation | P23: -50 | Q23: 50 | R23: 0 | S23: 50 | T23: -50
A24: 1448882 | B24: 45988 | C24: Levy Commission Leaseid-5832 Ref-LEVY - 15 CORONATION VILLAS | D24: 7.51 | F24: 179.39 | N24: 5832 | O24: Toko Muodzi Ross 15 Coronation Gardens | P24: -50 | Q24: 50 | R24: 0 | S24: 50 | T24: -50
A25: 1448886 | B25: 45988 | C25: Payment Leaseid-5824 Gibson Taruwinga 7 Coronation Ref-LEVY - 7 CORONATION VILLAS | E25: 50 | F25: 229.39 | N25: 5833 | O25: Emeldah Paradza 16 Coronation | P25: -50 | Q25: 50 | R25: 0 | S25: 0 | T25: 0
A26: 1448889 | B26: 45988 | C26: Levy Commission Leaseid-5824 Ref-LEVY - 7 CORONATION VILLAS | D26: 7.51 | F26: 221.88 | N26: 5834 | O26: Margaret Mushayi 17 Coronation | P26: -100 | Q26: 50 | R26: -50 | S26: 0 | T26: -50
A27: 1448893 | B27: 45988 | C27: Payment Leaseid-5819 Eva Mutangadura 2 Coronation Ref-LEVY - 2 CORONATION VILLAS | E27: 50 | F27: 271.88 | P27: -90 | Q27: 850 | R27: 760 | S27: 550 | T27: 210 | U27: =T11+T16+T22+T23+T24+T26 -> -300
A28: 1448896 | B28: 45988 | C28: Levy Commission Leaseid-5819 Ref-LEVY - 2 CORONATION VILLAS | D28: 7.51 | F28: 264.37 | T28: =U27*-1 -> 300
A29: 1450900 | B29: 45989 | C29: Payment Ref-BOREHOLE ASSESMENT | D29: 60 | F29: 204.37 | T29: =T27+T28 -> 510
A30: 1451086 | B30: 45989 | C30: Journal ref-STAFF SALARIES | D30: 543 | F30: -338.63
D31: 935.59 | E31: 550 | F31: -338.63

Sheet October25
A1: Statement | I1: Statement | Q1: Roll Over Summary
Q2: landlord - Coronation Gardens Onwers Association
A3: Account Holder: Coronation Gardens Onwers Association | I3: Account Holder: Coronation Gardens Onwers Association | Q3: Period: 2025-10-01 to 2025-10-31
Q4: Currency: USD
A5: Account ID:58345 | I5: Account ID:58344
A6: Account Currency:USD | I6: Account Currency:ZIG
A7: Transaction Period:2025-10-01 - 2025-10-31 | I7: Transaction Period:2025-10-01 - 2025-10-31
Q8: Property - Coronation Gardens, Greendale, Harare
A9: ID | B9: Date | C9: Description | D9: Debit | E9: Credit | F9: Balance | I9: ID | J9: Date | K9: Description | L9: Debit | M9: Credit | N9: Balance | Q9: LeaseID | R9: Tenant | S9: Balance B/F | T9: Amount Charged | U9: Amount Due | V9: Amount Paid | W9: Carried Forward
C10: Balance brought forward | F10: -358.6 | K10: Balance brought forward | N10: 0 | Q10: 5817 | R10: Agnes Furidze 1 Coronation | S10: 0 | T10: 50 | U10: 50 | V10: 100 | W10: -50
A11: 1428579 | B11: 45931 | C11: Payment Leaseid-5817 Agnes Furidze 1 Coronation Ref-LEVY-FURIDZE A-1 CORONATION-TRANSFER-23/09/25 | E11: 50 | F11: -308.6 | L11: 0 | M11: 0 | N11: 0 | Q11: 5819 | R11: Eva Mutangadura 2 Coronation | S11: 0 | T11: 50 | U11: 50 | V11: 100 | W11: -50
A12: 1428582 | B12: 45931 | C12: Levy Commission Leaseid-5817 Ref-LEVY-FURIDZE A-1 CORONATION-TRANSFER-23/09/25 | D12: 7.51 | F12: -316.11 | Q12: 5820 | R12: Kudzanayi Kachere 3 Coronation | S12: 0 | T12: 50 | U12: 50 | V12: 50 | W12: 0
A13: 1430381 | B13: 45933 | C13: Payment Leaseid-5831 Phillers Gwengo 14 Coronation Ref-LEVY - 14 CORONATION GARDENS | E13: 50 | F13: -266.11 | Q13: 5821 | R13: Hebros Dubai 4 Coronation | S13: 20 | T13: 50 | U13: 70 | V13: 50 | W13: 20
A14: 1430384 | B14: 45933 | C14: Levy Commission Leaseid-5831 Ref-LEVY - 14 CORONATION GARDENS | D14: 7.51 | F14: -273.62 | Q14: 5822 | R14: Tatenda Ngowe 5 Coronation | S14: 150 | T14: 50 | U14: 200 | V14: 200 | W14: 0
A15: 1430388 | B15: 45933 | C15: Payment Leaseid-5833 Emeldah Paradza 16 Coronation Ref-LEVY - 16 CORONATION GARDENS | E15: 50 | F15: -223.62 | Q15: 5823 | R15: Maud Silibaziso 6 Coronation | S15: 110 | T15: 50 | U15: 160 | V15: 50 | W15: 110
A16: 1430391 | B16: 45933 | C16: Levy Commission Leaseid-5833 Ref-LEVY - 16 CORONATION GARDENS | D16: 7.51 | F16: -231.13 | Q16: 5824 | R16: Gibson Taruwinga 7 Coronation | S16: 0 | T16: 50 | U16: 50 | V16: 100 | W16: -50
A17: 1430395 | B17: 45933 | C17: Payment Leaseid-5827 Dorothy R. S Makoni 10 Coronation Ref-LEVY - 10 CORONATION GARDENS | E17: 100 | F17: -131.13 | Q17: 5825 | R17: Lody Machiwenyika 8 Coronation | S17: 150 | T17: 50 | U17: 200 | V17: 0 | W17: 200
A18: 1430398 | B18: 45933 | C18: Levy Commission Leaseid-5827 Ref-LEVY - 10 CORONATION GARDENS | D18: 15.01 | F18: -146.14 | Q18: 5826 | R18: Unit 9 Coronation Gardens | S18: 100 | T18: 50 | U18: 150 | V18: 100 | W18: 50
A19: 1430402 | B19: 45933 | C19: Payment Leaseid-5834 Margaret Mushayi 17 Coronation Ref-LEVY - 17 CORONATION GARDENS | E19: 50 | F19: -96.14 | Q19: 5827 | R19: Dorothy R. S Makoni 10 Coronation | S19: 50 | T19: 50 | U19: 100 | V19: 150 | W19: -50
A20: 1430405 | B20: 45933 | C20: Levy Commission Leaseid-5834 Ref-LEVY - 17 CORONATION GARDENS | D20: 7.51 | F20: -103.65 | Q20: 5828 | R20: Farai Chivaura 11 Coronation | S20: 0 | T20: 50 | U20: 50 | V20: 20 | W20: 30
A21: 1430409 | B21: 45933 | C21: Payment Leaseid-5832 Toko Muodzi Ross 15 Coronation Gardens Ref-LEVY - 15 CORONATION GARDENS | E21: 50 | F21: -53.65 | Q21: 5829 | R21: Rose Chanakira 12 Coronation | S21: -50 | T21: 50 | U21: 0 | V21: 0 | W21: 0
A22: 1430412 | B22: 45933 | C22: Levy Commission Leaseid-5832 Ref-LEVY - 15 CORONATION GARDENS | D22: 7.51 | F22: -61.16 | Q22: 5830 | R22: Siketiwe Marima 13 Coronation | S22: 0 | T22: 50 | U22: 50 | V22: 100 | W22: -50
A23: 1430416 | B23: 45933 | C23: Payment Leaseid-5830 Siketiwe Marima 13 Coronation Ref-LEVY - 13 CORONATION GARDENS | E23: 50 | F23: -11.16 | Q23: 5831 | R23: Phillers Gwengo 14 Coronation | S23: 0 | T23: 50 | U23: 50 | V23: 100 | W23: -50
A24: 1430419 | B24: 45933 | C24: Levy Commission Leaseid-5830 Ref-LEVY - 13 CORONATION GARDENS | D24: 7.51 | F24: -18.67 | Q24: 5832 | R24: Toko Muodzi Ross 15 Coronation Gardens | S24: 0 | T24: 50 | U24: 50 | V24: 100 | W24: -50
A25: 1430423 | B25: 45933 | C25: Payment Leaseid-5824 Gibson Taruwinga 7 Coronation Ref-LEVY - 7 CORONATION GARDENS | E25: 50 | F25: 31.33 | Q25: 5833 | R25: Emeldah Paradza 16 Coronation | S25: 0 | T25: 50 | U25: 50 | V25: 100 | W25: -50
A26: 1430426 | B26: 45933 | C26: Levy Commission Leaseid-5824 Ref-LEVY - 7 CORONATION GARDENS | D26: 7.51 | F26: 23.82 | Q26: 5834 | R26: Margaret Mushayi 17 Coronation | S26: 0 | T26: 50 | U26: 50 | V26: 150 | W26: -100
A27: 1430430 | B27: 45933 | C27: Payment Leaseid-5823 Maud Silibaziso 6 Coronation Ref-LEVY - 6 CORONATION GARDENS | E27: 50 | F27: 73.82 | S27: 530 | T27: 850 | U27: 1380 | V27: 1470 | W27: -90
A28: 1430433 | B28: 45933 | C28: Levy Commission Leaseid-5823 Ref-LEVY - 6 CORONATION GARDENS | D28: 7.51 | F28: 66.31 | W28: =W10+W11+W16+W19+W22+W23+W24+W25+W26 -> -500 | X28: =W28*-1 -> 500
A29: 1430437 | B29: 45933 | C29: Payment Leaseid-5822 Tatenda Ngowe 5 Coronation Ref-LEVY - 5 CORONATION GARDENS | E29: 100 | F29: 166.31 | W29: =W27+X28 -> 410
A30: 1430440 | B30: 45933 | C30: Levy Commission Leaseid-5822 Ref-LEVY - 5 CORONATION GARDENS | D30: 15.01 | F30: 151.3
A31: 1430444 | B31: 45933 | C31: Payment Leaseid-5819 Eva Mutangadura 2 Coronation Ref-LEVY - 2 CORONATION GARDENS | E31: 50 | F31: 201.3
A32: 1430447 | B32: 45933 | C32: Levy Commission Leaseid-5819 Ref-LEVY - 2 CORONATION GARDENS | D32: 7.51 | F32: 193.79
A33: 1430884 | B33: 45936 | C33: Payment Leaseid-5820 Kudzanayi Kachere 3 Coronation Ref-LEVY-KACHERE K-3 CORONATION-TRANSFER-02/10/25 | E33: 50 | F33: 243.79
A34: 1430887 | B34: 45936 | C34: Levy Commission Leaseid-5820 Ref-LEVY-KACHERE K-3 CORONATION-TRANSFER-02/10/25 | D34: 7.51 | F34: 236.28
A35: 1432843 | B35: 45938 | C35: Payment Leaseid-5821 Hebros Dubai 4 Coronation Ref-LEVY-DUBAI D-4 CORONATION-TRANSFER-06/10/25 | E35: 50 | F35: 286.28
A36: 1432846 | B36: 45938 | C36: Levy Commission Leaseid-5821 Ref-LEVY-DUBAI D-4 CORONATION-TRANSFER-06/10/25 | D36: 7.51 | F36: 278.77
A37: 1432988 | B37: 45938 | C37: Payment Ref-GATE REPAIRS | D37: 138 | F37: 140.77
A38: 1433802 | B38: 45939 | C38: Payment Ref-UPPER MANYAME -BOREHOLE LEVY | D38: 50 | F38: 90.77
A39: 1433918 | B39: 45940 | C39: Payment Leaseid-5828 Farai Chivaura 11 Coronation Ref-LEVY - 11 CORONATION/gate rail repairs | E39: 20 | F39: 110.77
A40: 1433921 | B40: 45940 | C40: Levy Commission Leaseid-5828 Ref-LEVY - 11 CORONATION/gate rail repairs | D40: 3 | F40: 107.77
A41: 1434286 | B41: 45940 | C41: Payment Ref-GATE REPAIRS RAIL | D41: 20 | F41: 87.77
A42: 1434618 | B42: 45943 | C42: Journal ref-RATES -UPPER MANYAME | D42: 90 | F42: -2.23
A43: 1434620 | B43: 45943 | C43: Journal ref-BANK CHARGES -UPPER MANYAME | D43: 2.7 | F43: -4.93
A44: 1435054 | B44: 45944 | C44: Payment Leaseid-5826 Unit 9 Coronation Gardens Ref-LEVY-9 CORONATION-ECOCASH-03/10/25 | E44: 100 | F44: 95.07
A45: 1435057 | B45: 45944 | C45: Levy Commission Leaseid-5826 Ref-LEVY-9 CORONATION-ECOCASH-03/10/25 | D45: 15.01 | F45: 80.06
A46: 1437490 | B46: 45958 | C46: Payment Leaseid-5817 Agnes Furidze 1 Coronation Ref-LEVY-FURIDZE A-1 CORONATION-TRANSFER-23/10/25 | E46: 50 | F46: 130.06
A47: 1437493 | B47: 45958 | C47: Levy Commission Leaseid-5817 Ref-LEVY-FURIDZE A-1 CORONATION-TRANSFER-23/10/25 | D47: 7.51 | F47: 122.55
A48: 1437590 | B48: 45958 | C48: Payment Leaseid-5827 Dorothy R. S Makoni 10 Coronation Ref-LEVY - 10 CORONATION GARDENS | E48: 50 | F48: 172.55
A49: 1437593 | B49: 45958 | C49: Levy Commission Leaseid-5827 Ref-LEVY - 10 CORONATION GARDENS | D49: 7.51 | F49: 165.04
A50: 1437597 | B50: 45958 | C50: Payment Leaseid-5834 Margaret Mushayi 17 Coronation Ref-LEVY - 17 CORONATION GARDENS | E50: 100 | F50: 265.04
A51: 1437600 | B51: 45958 | C51: Levy Commission Leaseid-5834 Ref-LEVY - 17 CORONATION GARDENS | D51: 15.01 | F51: 250.03
A52: 1437604 | B52: 45958 | C52: Payment Leaseid-5833 Emeldah Paradza 16 Coronation Ref-LEVY - 16 CORONATION GARDENS | E52: 50 | F52: 300.03
A53: 1437607 | B53: 45958 | C53: Levy Commission Leaseid-5833 Ref-LEVY - 16 CORONATION GARDENS | D53: 7.51 | F53: 292.52
A54: 1437611 | B54: 45958 | C54: Payment Leaseid-5832 Toko Muodzi Ross 15 Coronation Gardens Ref-LEVY - 15 CORONATION GARDENS | E54: 50 | F54: 342.52
A55: 1437614 | B55: 45958 | C55: Levy Commission Leaseid-5832 Ref-LEVY - 15 CORONATION GARDENS | D55: 7.51 | F55: 335.01
A56: 1437646 | B56: 45958 | C56: Payment Leaseid-5830 Siketiwe Marima 13 Coronation Ref-LEVY - 13 CORONATION GARDENS | E56: 50 | F56: 385.01
A57: 1437649 | B57: 45958 | C57: Levy Commission Leaseid-5830 Ref-LEVY - 13 CORONATION GARDENS | D57: 7.51 | F57: 377.5
A58: 1437653 | B58: 45958 | C58: Payment Leaseid-5822 Tatenda Ngowe 5 Coronation Ref-LEVY - 5 CORONATION GARDENS | E58: 100 | F58: 477.5
A59: 1437656 | B59: 45958 | C59: Levy Commission Leaseid-5822 Ref-LEVY - 5 CORONATION GARDENS | D59: 15.01 | F59: 462.49
A60: 1437660 | B60: 45958 | C60: Payment Leaseid-5824 Gibson Taruwinga 7 Coronation Ref-LEVY - 7 CORONATION GARDENS | E60: 50 | F60: 512.49
A61: 1437663 | B61: 45958 | C61: Levy Commission Leaseid-5824 Ref-LEVY - 7 CORONATION GARDENS | D61: 7.51 | F61: 504.98
A62: 1437667 | B62: 45958 | C62: Payment Leaseid-5819 Eva Mutangadura 2 Coronation Ref-LEVY - 2 CORONATION GARDENS | E62: 50 | F62: 554.98
A63: 1437670 | B63: 45958 | C63: Levy Commission Leaseid-5819 Ref-LEVY - 2 CORONATION GARDENS | D63: 7.51 | F63: 547.47
A64: 1438302 | B64: 45961 | C64: Payment Leaseid-5831 Phillers Gwengo 14 Coronation Ref-LEVY - 14 CORONATION GARDENS | E64: 50 | F64: 597.47
A65: 1438305 | B65: 45961 | C65: Levy Commission Leaseid-5831 Ref-LEVY - 14 CORONATION GARDENS | D65: 7.51 | F65: 589.96
A66: 1438878 | B66: 45961 | C66: Payment Ref-STAFF SALARIES | D66: 543 | F66: 46.96
D67: 1064.44 | E67: 1470 | F67: 46.96

Sheet Sept
A1: Statement | J1: Statement | R1: Roll Over Summary
R2: landlord - Coronation Gardens Onwers Association
A3: Account Holder: Coronation Gardens Onwers Association | J3: Account Holder: Coronation Gardens Onwers Association | R3: Period: 2025-09-01 to 2025-09-30
R4: Currency: USD
A5: Account ID:58345 | J5: Account ID:58344
A6: Account Currency:USD | J6: Account Currency:ZIG
A7: Transaction Period:2025-09-01 - 2025-09-30 | J7: Transaction Period:2025-09-01 - 2025-09-30
R8: Property - Coronation Gardens, Greendale, Harare
A9: ID | B9: Date | C9: Description | D9: Debit | E9: Credit | F9: Balance | J9: ID | K9: Date | L9: Description | M9: Debit | N9: Credit | O9: Balance | R9: LeaseID | S9: Tenant | T9: Balance B/F | U9: Amount Charged | V9: Amount Due | W9: Amount Paid | X9: Carried Forward
C10: Balance brought forward | F10: -352.95 | L10: Balance brought forward | O10: 0 | R10: 5817 | S10: Agnes Furidze 1 Coronation | T10: 0 | U10: 50 | V10: 50 | W10: 50 | X10: 0
A11: 1415193 | B11: 45902 | C11: Payment Leaseid-5828 Farai Chivaura 11 Coronation Ref-LEVY - 11 CORONATION GARDENS | E11: 50 | F11: -302.95 | M11: 0 | N11: 0 | O11: 0 | R11: 5819 | S11: Eva Mutangadura 2 Coronation | T11: 0 | U11: 50 | V11: 50 | W11: 50 | X11: 0
A12: 1415196 | B12: 45902 | C12: Levy Commission Leaseid-5828 Ref-LEVY - 11 CORONATION GARDENS | D12: 7.51 | F12: -310.46 | R12: 5820 | S12: Kudzanayi Kachere 3 Coronation | T12: 0 | U12: 50 | V12: 50 | W12: 50 | X12: 0
A13: 1415200 | B13: 45902 | C13: Payment Leaseid-5834 Margaret Mushayi 17 Coronation Ref-LEVY - 17 CORONATION GARDENS | E13: 50 | F13: -260.46 | R13: 5821 | S13: Hebros Dubai 4 Coronation | T13: 20 | U13: 50 | V13: 70 | W13: 50 | X13: 20
A14: 1415203 | B14: 45902 | C14: Levy Commission Leaseid-5834 Ref-LEVY - 17 CORONATION GARDENS | D14: 7.51 | F14: -267.97 | R14: 5822 | S14: Tatenda Ngowe 5 Coronation | T14: 100 | U14: 50 | V14: 150 | W14: 0 | X14: 150
A15: 1415207 | B15: 45902 | C15: Payment Leaseid-5827 Dorothy R. S Makoni 10 Coronation Ref-LEVY - 10 CORONATION GARDENS | E15: 50 | F15: -217.97 | R15: 5823 | S15: Maud Silibaziso 6 Coronation | T15: 110 | U15: 50 | V15: 160 | W15: 50 | X15: 110
A16: 1415210 | B16: 45902 | C16: Levy Commission Leaseid-5827 Ref-LEVY - 10 CORONATION GARDENS | D16: 7.51 | F16: -225.48 | R16: 5824 | S16: Gibson Taruwinga 7 Coronation | T16: 0 | U16: 50 | V16: 50 | W16: 50 | X16: 0
A17: 1415214 | B17: 45902 | C17: Payment Leaseid-5833 Emeldah Paradza 16 Coronation Ref-LEVY - 16 CORONATION GARDENS | E17: 50 | F17: -175.48 | R17: 5825 | S17: Lody Machiwenyika 8 Coronation | T17: 100 | U17: 50 | V17: 150 | W17: 0 | X17: 150
A18: 1415217 | B18: 45902 | C18: Levy Commission Leaseid-5833 Ref-LEVY - 16 CORONATION GARDENS | D18: 7.51 | F18: -182.99 | R18: 5826 | S18: Unit 9 Coronation Gardens | T18: 50 | U18: 50 | V18: 100 | W18: 0 | X18: 100
A19: 1415221 | B19: 45902 | C19: Payment Leaseid-5829 Rose Chanakira 12 Coronation Ref-LEVY - 12 CORONATION GARDENS | E19: 50 | F19: -132.99 | R19: 5827 | S19: Dorothy R. S Makoni 10 Coronation | T19: 50 | U19: 50 | V19: 100 | W19: 50 | X19: 50
A20: 1415224 | B20: 45902 | C20: Levy Commission Leaseid-5829 Ref-LEVY - 12 CORONATION GARDENS | D20: 7.51 | F20: -140.5 | R20: 5828 | S20: Farai Chivaura 11 Coronation | T20: 0 | U20: 50 | V20: 50 | W20: 50 | X20: 0
A21: 1415228 | B21: 45902 | C21: Payment Leaseid-5832 Toko Muodzi Ross 15 Coronation Gardens Ref-LEVY - 15 CORONATION GARDENS | E21: 50 | F21: -90.5 | R21: 5829 | S21: Rose Chanakira 12 Coronation | T21: 0 | U21: 50 | V21: 50 | W21: 100 | X21: -50
A22: 1415231 | B22: 45902 | C22: Levy Commission Leaseid-5832 Ref-LEVY - 15 CORONATION GARDENS | D22: 7.51 | F22: -98.01 | R22: 5830 | S22: Siketiwe Marima 13 Coronation | T22: 0 | U22: 50 | V22: 50 | W22: 50 | X22: 0
A23: 1415235 | B23: 45902 | C23: Payment Leaseid-5830 Siketiwe Marima 13 Coronation Ref-LEVY - 13 CORONATION VILLAS | E23: 50 | F23: -48.01 | R23: 5831 | S23: Phillers Gwengo 14 Coronation | T23: 0 | U23: 50 | V23: 50 | W23: 50 | X23: 0
A24: 1415238 | B24: 45902 | C24: Levy Commission Leaseid-5830 Ref-LEVY - 13 CORONATION VILLAS | D24: 7.51 | F24: -55.52 | R24: 5832 | S24: Toko Muodzi Ross 15 Coronation Gardens | T24: 0 | U24: 50 | V24: 50 | W24: 50 | X24: 0
A25: 1415242 | B25: 45902 | C25: Payment Leaseid-5831 Phillers Gwengo 14 Coronation Ref-LEVY - 14 CORONATION GARDENS | E25: 50 | F25: -5.52 | R25: 5833 | S25: Emeldah Paradza 16 Coronation | T25: 0 | U25: 50 | V25: 50 | W25: 50 | X25: 0
A26: 1415245 | B26: 45902 | C26: Levy Commission Leaseid-5831 Ref-LEVY - 14 CORONATION GARDENS | D26: 7.51 | F26: -13.03 | R26: 5834 | S26: Margaret Mushayi 17 Coronation | T26: 0 | U26: 50 | V26: 50 | W26: 50 | X26: 0
A27: 1415249 | B27: 45902 | C27: Payment Leaseid-5823 Maud Silibaziso 6 Coronation Ref-LEVY - 6 CORONATION VILLAS | E27: 50 | F27: 36.97 | T27: 430 | U27: 850 | V27: 1280 | W27: 750 | X27: 530
A28: 1415252 | B28: 45902 | C28: Levy Commission Leaseid-5823 Ref-LEVY - 6 CORONATION VILLAS | D28: 7.51 | F28: 29.46 | X28: =X21*-1 -> 50
A29: 1415256 | B29: 45902 | C29: Payment Leaseid-5819 Eva Mutangadura 2 Coronation Ref-LEVY - 2 CORONATION GARDENS | E29: 50 | F29: 79.46 | X29: =X27+X28 -> 580
A30: 1415259 | B30: 45902 | C30: Levy Commission Leaseid-5819 Ref-LEVY - 2 CORONATION GARDENS | D30: 7.51 | F30: 71.95
A31: 1415263 | B31: 45902 | C31: Payment Leaseid-5824 Gibson Taruwinga 7 Coronation Ref-LEVY - 7 CORONATION VILLAS | E31: 50 | F31: 121.95
A32: 1415266 | B32: 45902 | C32: Levy Commission Leaseid-5824 Ref-LEVY - 7 CORONATION VILLAS | D32: 7.51 | F32: 114.44
A33: 1415270 | B33: 45902 | C33: Payment Leaseid-5829 Rose Chanakira 12 Coronation Ref-LEVY - 12 CORONATION GARDENS | E33: 50 | F33: 164.44
A34: 1415273 | B34: 45902 | C34: Levy Commission Leaseid-5829 Ref-LEVY - 12 CORONATION GARDENS | D34: 7.51 | F34: 156.93
A35: 1417297 | B35: 45903 | C35: Payment Leaseid-5817 Agnes Furidze 1 Coronation Ref-LEVY 1 CORONATION FURIDZE TRANSFER 25/08/25 | E35: 50 | F35: 206.93
A36: 1417300 | B36: 45903 | C36: Levy Commission Leaseid-5817 Ref-LEVY 1 CORONATION FURIDZE TRANSFER 25/08/25 | D36: 7.51 | F36: 199.42
A37: 1423993 | B37: 45904 | C37: Payment Leaseid-5820 Kudzanayi Kachere 3 Coronation Ref-LEVY-KACHERE K-3 CORONATION-ECOCASH-04/09/25 | E37: 50 | F37: 249.42
A38: 1423996 | B38: 45904 | C38: Levy Commission Leaseid-5820 Ref-LEVY-KACHERE K-3 CORONATION-ECOCASH-04/09/25 | D38: 7.51 | F38: 241.91
A39: 1424060 | B39: 45916 | C39: Payment Leaseid-5821 Hebros Dubai 4 Coronation Ref-LEVY-DUBAI H-4 CORONATION-TRANSFER-09/09/25 | E39: 50 | F39: 291.91
A40: 1424063 | B40: 45916 | C40: Levy Commission Leaseid-5821 Ref-LEVY-DUBAI H-4 CORONATION-TRANSFER-09/09/25 | D40: 7.51 | F40: 284.4
A41: 1424246 | B41: 45916 | C41: Payment Ref- RELIEVE SECURITY GUARD -MR TSABORA | D41: 90 | F41: 194.4
A42: 1425659 | B42: 45923 | C42: Payment Ref-MURARA BROOMS | D42: 10 | F42: 184.4
A43: 1428449 | B43: 45930 | C43: Journal ref-STAFF SALARIES -SPTEMBER 2025 | D43: 543 | F43: -358.6
D44: 755.65 | E44: 750 | F44: -358.6

Sheet August25
A1: Statement | J1: Roll Over Summary
J2: landlord - Coronation Gardens Onwers Association
A3: Account Holder: Coronation Gardens Onwers Association | J3: Period: 2025-08-01 to 2025-08-31
J4: Currency: USD
A5: Account ID:58345
A6: Account Currency:USD
A7: Transaction Period:2025-08-01 - 2025-08-31
J8: Property - Coronation Gardens, Greendale, Harare
A9: ID | B9: Date | C9: Description | D9: Debit | E9: Credit | F9: Balance | J9: LeaseID | K9: Tenant | L9: Balance B/F | M9: Amount Charged | N9: Amount Due | O9: Amount Paid | P9: Carried Forward
C10: Balance brought forward | F10: -362.33 | J10: 5817 | K10: Agnes Furidze 1 Coronation | L10: 0 | M10: 50 | N10: 50 | O10: 50 | P10: 0
A11: 1406793 | B11: 45875 | C11: Payment Leaseid-5834 Margaret Mushayi 17 Coronation Ref-LEVY - 17 CORONATION GARDENS | E11: 50 | F11: -312.33 | J11: 5819 | K11: Eva Mutangadura 2 Coronation | L11: 0 | M11: 50 | N11: 50 | O11: 50 | P11: 0
A12: 1406796 | B12: 45875 | C12: Levy Commission Leaseid-5834 Ref-LEVY - 17 CORONATION GARDENS | D12: 7.51 | F12: -319.84 | J12: 5820 | K12: Kudzanayi Kachere 3 Coronation | L12: -50 | M12: 50 | N12: 0 | O12: 0 | P12: 0
A13: 1406800 | B13: 45875 | C13: Payment Leaseid-5828 Farai Chivaura 11 Coronation Ref-LEVY - 11 CORONATION GARDENS | E13: 100 | F13: -219.84 | J13: 5821 | K13: Hebros Dubai 4 Coronation | L13: 20 | M13: 50 | N13: 70 | O13: 50 | P13: 20
A14: 1406803 | B14: 45875 | C14: Levy Commission Leaseid-5828 Ref-LEVY - 11 CORONATION GARDENS | D14: 15.01 | F14: -234.85 | J14: 5822 | K14: Tatenda Ngowe 5 Coronation | L14: 50 | M14: 50 | N14: 100 | O14: 0 | P14: 100
A15: 1406807 | B15: 45875 | C15: Payment Leaseid-5829 Rose Chanakira 12 Coronation Ref-LEVY - 12 CORONATION GARDENS | E15: 50 | F15: -184.85 | J15: 5823 | K15: Maud Silibaziso 6 Coronation | L15: 60 | M15: 50 | N15: 110 | O15: 0 | P15: 110
A16: 1406810 | B16: 45875 | C16: Levy Commission Leaseid-5829 Ref-LEVY - 12 CORONATION GARDENS | D16: 7.51 | F16: -192.36 | J16: 5824 | K16: Gibson Taruwinga 7 Coronation | L16: 0 | M16: 50 | N16: 50 | O16: 50 | P16: 0
A17: 1406814 | B17: 45875 | C17: Payment Leaseid-5831 Phillers Gwengo 14 Coronation Ref-LEVY - 14 CORONATION GARDENS | E17: 50 | F17: -142.36 | J17: 5825 | K17: Lody Machiwenyika 8 Coronation | L17: 50 | M17: 50 | N17: 100 | O17: 0 | P17: 100
A18: 1406817 | B18: 45875 | C18: Levy Commission Leaseid-5831 Ref-LEVY - 14 CORONATION GARDENS | D18: 7.51 | F18: -149.87 | J18: 5826 | K18: Unit 9 Coronation Gardens | L18: 50 | M18: 50 | N18: 100 | O18: 50 | P18: 50
A19: 1406828 | B19: 45875 | C19: Payment Leaseid-5832 Toko Muodzi Ross 15 Coronation Gardens Ref-LEVY - 15 CORONATION VILLAS | E19: 50 | F19: -99.87 | J19: 5827 | K19: Dorothy R. S Makoni 10 Coronation | L19: 0 | M19: 50 | N19: 50 | O19: 0 | P19: 50
A20: 1406831 | B20: 45875 | C20: Levy Commission Leaseid-5832 Ref-LEVY - 15 CORONATION VILLAS | D20: 7.51 | F20: -107.38 | J20: 5828 | K20: Farai Chivaura 11 Coronation | L20: 50 | M20: 50 | N20: 100 | O20: 100 | P20: 0
A21: 1406835 | B21: 45875 | C21: Payment Leaseid-5830 Siketiwe Marima 13 Coronation Ref-LEVY - 13 CORONATION VILLAS | E21: 50 | F21: -57.38 | J21: 5829 | K21: Rose Chanakira 12 Coronation | L21: 0 | M21: 50 | N21: 50 | O21: 50 | P21: 0
A22: 1406838 | B22: 45875 | C22: Levy Commission Leaseid-5830 Ref-LEVY - 13 CORONATION VILLAS | D22: 7.51 | F22: -64.89 | J22: 5830 | K22: Siketiwe Marima 13 Coronation | L22: 0 | M22: 50 | N22: 50 | O22: 50 | P22: 0
A23: 1406842 | B23: 45875 | C23: Payment Leaseid-5833 Emeldah Paradza 16 Coronation Ref-LEVY - 16 CORONATION VILLAS | E23: 50 | F23: -14.89 | J23: 5831 | K23: Phillers Gwengo 14 Coronation | L23: 0 | M23: 50 | N23: 50 | O23: 50 | P23: 0
A24: 1406845 | B24: 45875 | C24: Levy Commission Leaseid-5833 Ref-LEVY - 16 CORONATION VILLAS | D24: 7.51 | F24: -22.4 | J24: 5832 | K24: Toko Muodzi Ross 15 Coronation Gardens | L24: 0 | M24: 50 | N24: 50 | O24: 50 | P24: 0
A25: 1406849 | B25: 45875 | C25: Payment Leaseid-5826 Unit 9 Coronation Gardens Ref-LEVY - 9 CORONATION VILLAS | E25: 50 | F25: 27.6 | J25: 5833 | K25: Emeldah Paradza 16 Coronation | L25: 0 | M25: 50 | N25: 50 | O25: 50 | P25: 0
A26: 1406852 | B26: 45875 | C26: Levy Commission Leaseid-5826 Ref-LEVY - 9 CORONATION VILLAS | D26: 7.51 | F26: 20.09 | J26: 5834 | K26: Margaret Mushayi 17 Coronation | L26: 0 | M26: 50 | N26: 50 | O26: 50 | P26: 0
A27: 1406856 | B27: 45875 | C27: Payment Leaseid-5819 Eva Mutangadura 2 Coronation Ref-LEVY - 2 CORONATION VILLAS | E27: 50 | F27: 70.09 | L27: 230 | M27: 850 | N27: 1080 | O27: 650 | P27: 430
A28: 1406859 | B28: 45875 | C28: Levy Commission Leaseid-5819 Ref-LEVY - 2 CORONATION VILLAS | D28: 7.51 | F28: 62.58
A29: 1407652 | B29: 45876 | C29: Payment Leaseid-5817 Agnes Furidze 1 Coronation Ref-LEVY-FURIDZE A-1 CORONATION-TRANSFER-23/07/25 | E29: 50 | F29: 112.58
A30: 1407655 | B30: 45876 | C30: Levy Commission Leaseid-5817 Ref-LEVY-FURIDZE A-1 CORONATION-TRANSFER-23/07/25 | D30: 7.51 | F30: 105.07
A31: 1407681 | B31: 45876 | C31: Payment Leaseid-5821 Hebros Dubai 4 Coronation Ref-LEVY - 4 CORONATION GARDENS | E31: 50 | F31: 155.07
A32: 1407684 | B32: 45876 | C32: Levy Commission Leaseid-5821 Ref-LEVY - 4 CORONATION GARDENS | D32: 7.51 | F32: 147.56
A33: 1407730 | B33: 45876 | C33: Payment Leaseid-5824 Gibson Taruwinga 7 Coronation Ref-LEVY-TARUWINGA G-7 CORONATION-TRANSFER-06/08/25 | E33: 50 | F33: 197.56
A34: 1407733 | B34: 45876 | C34: Levy Commission Leaseid-5824 Ref-LEVY-TARUWINGA G-7 CORONATION-TRANSFER-06/08/25 | D34: 7.51 | F34: 190.05
A35: 1414512 | B35: 45899 | C35: Journal ref-STAFF SALARIES | D35: 543 | F35: -352.95
D36: 640.62 | E36: 650 | F36: -352.95

Sheet june25
A1: Statement | J1: Roll Over Summary
J2: landlord - Coronation Gardens Onwers Association
A3: Account Holder: Coronation Gardens Onwers Association | J3: Period: 2025-06-01 to 2025-06-30
J4: Currency: USD
A5: Account ID:58345
A6: Account Currency:USD
A7: Transaction Period:2025-06-01 - 2025-06-30
J8: Property - Coronation Gardens, Greendale, Harare
A9: ID | B9: Date | C9: Description | D9: Debit | E9: Credit | F9: Balance | J9: LeaseID | K9: Tenant | L9: Balance B/F | M9: Amount Charged | N9: Amount Due | O9: Amount Paid | P9: Carried Forward
C10: Balance brought forward | F10: -256.83 | J10: 5817 | K10: Agnes Furidze 1 Coronation | L10: 0 | M10: 50 | N10: 50 | O10: 100 | P10: -50
A11: 1383040 | B11: 45810 | C11: Payment Leaseid-5820 Kudzanayi Kachere 3 Coronation Ref-LEVY-KACHERE K-3 CORONATION-TRANSFER-27/05/25 | E11: 50 | F11: -206.83 | J11: 5819 | K11: Eva Mutangadura 2 Coronation | L11: 0 | M11: 50 | N11: 50 | O11: 50 | P11: 0
A12: 1383043 | B12: 45810 | C12: Levy Commission Leaseid-5820 Ref-LEVY-KACHERE K-3 CORONATION-TRANSFER-27/05/25 | D12: 7.51 | F12: -214.34 | J12: 5820 | K12: Kudzanayi Kachere 3 Coronation | L12: 0 | M12: 50 | N12: 50 | O12: 50 | P12: 0
A13: 1383047 | B13: 45810 | C13: Payment Leaseid-5817 Agnes Furidze 1 Coronation Ref-LEVY-FURIDZE A-1 CORONATION-TRANSFER-23/05/25 | E13: 50 | F13: -164.34 | J13: 5821 | K13: Hebros Dubai 4 Coronation | L13: 20 | M13: 50 | N13: 70 | O13: 50 | P13: 20
A14: 1383050 | B14: 45810 | C14: Levy Commission Leaseid-5817 Ref-LEVY-FURIDZE A-1 CORONATION-TRANSFER-23/05/25 | D14: 7.51 | F14: -171.85 | J14: 5822 | K14: Tatenda Ngowe 5 Coronation | L14: 50 | M14: 50 | N14: 100 | O14: 100 | P14: 0
A15: 1388386 | B15: 45812 | C15: Payment Leaseid-5822 Tatenda Ngowe 5 Coronation Ref-LEVY-NGOWE T-5 CORONATION-TRANSFER-04/06/25 | E15: 100 | F15: -71.85 | J15: 5823 | K15: Maud Silibaziso 6 Coronation | L15: 68 | M15: 50 | N15: 118 | O15: 50 | P15: 68
A16: 1388389 | B16: 45812 | C16: Levy Commission Leaseid-5822 Ref-LEVY-NGOWE T-5 CORONATION-TRANSFER-04/06/25 | D16: 15.01 | F16: -86.86 | J16: 5824 | K16: Gibson Taruwinga 7 Coronation | L16: 0 | M16: 50 | N16: 50 | O16: 50 | P16: 0
A17: 1385227 | B17: 45813 | C17: Payment Leaseid-5834 Margaret Mushayi 17 Coronation Ref-LEVY - 17 CORONATION | E17: 50 | F17: -36.86 | J17: 5825 | K17: Lody Machiwenyika 8 Coronation | L17: 150 | M17: 50 | N17: 200 | O17: 200 | P17: 0
A18: 1385230 | B18: 45813 | C18: Levy Commission Leaseid-5834 Ref-LEVY - 17 CORONATION | D18: 7.51 | F18: -44.37 | J18: 5826 | K18: Unit 9 Coronation Gardens | L18: 0 | M18: 50 | N18: 50 | O18: 0 | P18: 50
A19: 1385234 | B19: 45813 | C19: Payment Leaseid-5831 Phillers Gwengo 14 Coronation Ref-LEVY - 14 CORONATION | E19: 50 | F19: 5.63 | J19: 5827 | K19: Dorothy R. S Makoni 10 Coronation | L19: 0 | M19: 50 | N19: 50 | O19: 0 | P19: 50
A20: 1385237 | B20: 45813 | C20: Levy Commission Leaseid-5831 Ref-LEVY - 14 CORONATION | D20: 7.51 | F20: -1.88 | J20: 5828 | K20: Farai Chivaura 11 Coronation | L20: 20 | M20: 50 | N20: 70 | O20: 70 | P20: 0
A21: 1385241 | B21: 45813 | C21: Payment Leaseid-5833 Emeldah Paradza 16 Coronation Ref-LEVY - 16 CORONATION | E21: 50 | F21: 48.12 | J21: 5829 | K21: Rose Chanakira 12 Coronation | L21: 0 | M21: 50 | N21: 50 | O21: 100 | P21: -50
A22: 1385244 | B22: 45813 | C22: Levy Commission Leaseid-5833 Ref-LEVY - 16 CORONATION | D22: 7.51 | F22: 40.61 | J22: 5830 | K22: Siketiwe Marima 13 Coronation | L22: -50 | M22: 50 | N22: 0 | O22: 0 | P22: 0
A23: 1385248 | B23: 45813 | C23: Payment Leaseid-5824 Gibson Taruwinga 7 Coronation Ref-LEVY - 7 CORONATION | E23: 50 | F23: 90.61 | J23: 5831 | K23: Phillers Gwengo 14 Coronation | L23: 0 | M23: 50 | N23: 50 | O23: 50 | P23: 0
A24: 1385251 | B24: 45813 | C24: Levy Commission Leaseid-5824 Ref-LEVY - 7 CORONATION | D24: 7.51 | F24: 83.1 | J24: 5832 | K24: Toko Muodzi Ross 15 Coronation Gardens | L24: 0 | M24: 50 | N24: 50 | O24: 50 | P24: 0
A25: 1385255 | B25: 45813 | C25: Payment Leaseid-5829 Rose Chanakira 12 Coronation Ref-LEVY - 12 CORONATION | E25: 50 | F25: 133.1 | J25: 5833 | K25: Emeldah Paradza 16 Coronation | L25: 0 | M25: 50 | N25: 50 | O25: 50 | P25: 0
A26: 1385258 | B26: 45813 | C26: Levy Commission Leaseid-5829 Ref-LEVY - 12 CORONATION | D26: 7.51 | F26: 125.59 | J26: 5834 | K26: Margaret Mushayi 17 Coronation | L26: 0 | M26: 50 | N26: 50 | O26: 50 | P26: 0
A27: 1385262 | B27: 45813 | C27: Payment Leaseid-5828 Farai Chivaura 11 Coronation Ref-LEVY - 11 CORONATION | E27: 50 | F27: 175.59 | L27: 258 | M27: 850 | N27: 1108 | O27: 1020 | P27: 88
A28: 1385265 | B28: 45813 | C28: Levy Commission Leaseid-5828 Ref-LEVY - 11 CORONATION | D28: 7.51 | F28: 168.08 | P28: =P10+P21 -> -100
A29: 1385269 | B29: 45813 | C29: Payment Leaseid-5832 Toko Muodzi Ross 15 Coronation Gardens Ref-LEVY - 15 CORONATION | E29: 50 | F29: 218.08 | P29: =P28*-1 -> 100
A30: 1385272 | B30: 45813 | C30: Levy Commission Leaseid-5832 Ref-LEVY - 15 CORONATION | D30: 7.51 | F30: 210.57 | P30: =P27+P29 -> 188
A31: 1385283 | B31: 45813 | C31: Payment Leaseid-5823 Maud Silibaziso 6 Coronation Ref-LEVY - 6 CORONATION | E31: 50 | F31: 260.57
A32: 1385286 | B32: 45813 | C32: Levy Commission Leaseid-5823 Ref-LEVY - 6 CORONATION | D32: 7.51 | F32: 253.06
A33: 1385290 | B33: 45813 | C33: Payment Leaseid-5819 Eva Mutangadura 2 Coronation Ref-LEVY - 2 CORONATION | E33: 50 | F33: 303.06
A34: 1385293 | B34: 45813 | C34: Levy Commission Leaseid-5819 Ref-LEVY - 2 CORONATION | D34: 7.51 | F34: 295.55
A35: 1385311 | B35: 45813 | C35: Payment Leaseid-5829 Rose Chanakira 12 Coronation Ref-LEVY - 12 CORONATION | E35: 50 | F35: 345.55
A36: 1385314 | B36: 45813 | C36: Levy Commission Leaseid-5829 Ref-LEVY - 12 CORONATION | D36: 7.51 | F36: 338.04
A37: 1385693 | B37: 45814 | C37: Payment Leaseid-5821 Hebros Dubai 4 Coronation Ref-JUN LEVY - 4 CORONATION | E37: 50 | F37: 388.04
A38: 1385696 | B38: 45814 | C38: Levy Commission Leaseid-5821 Ref-JUN LEVY - 4 CORONATION | D38: 7.51 | F38: 380.53
A39: 1388131 | B39: 45817 | C39: Payment Ref-ELECTRICAL CABLES | D39: 58 | F39: 322.53
A40: 1389759 | B40: 45825 | C40: Payment Ref-UPPER MANYAME | D40: 80 | F40: 242.53
A41: 1389442 | B41: 45828 | C41: Payment Leaseid-5825 Lody Machiwenyika 8 Coronation Ref-LEVY/zesa - 8 CORONATION | E41: 200 | F41: 442.53
A42: 1389445 | B42: 45828 | C42: Levy Commission Leaseid-5825 Ref-LEVY/zesa - 8 CORONATION | D42: 30.02 | F42: 412.51
A43: 1389449 | B43: 45828 | C43: Payment Leaseid-5828 Farai Chivaura 11 Coronation Ref-LEVY/gate repairs - 11 CORONATION | E43: 20 | F43: 432.51
A44: 1389452 | B44: 45828 | C44: Levy Commission Leaseid-5828 Ref-LEVY/gate repairs - 11 CORONATION | D44: 3 | F44: 429.51
A45: 1389959 | B45: 45828 | C45: Payment Ref-GATE REPAIRS | D45: 20 | F45: 409.51
A46: 1389961 | B46: 45828 | C46: Payment Ref-ZESA PURCHASE | D46: 200 | F46: 209.51
A47: 1390477 | B47: 45835 | C47: Payment Leaseid-5817 Agnes Furidze 1 Coronation Ref-LEVY-FURIDZE A-1 CORONATION-TRANSFER-24/06/25 | E47: 50 | F47: 259.51
A48: 1390480 | B48: 45835 | C48: Levy Commission Leaseid-5817 Ref-LEVY-FURIDZE A-1 CORONATION-TRANSFER-24/06/25 | D48: 7.51 | F48: 252
A49: 1393461 | B49: 45838 | C49: Journal ref-STAFF SALARIES | D49: 543 | F49: -291
D50: 1054.17 | E50: 1020 | F50: -291

Sheet May25
A1: Statement | J1: Statement | R1: Roll Over Summary
R2: landlord - Coronation Gardens Onwers Association
A3: Account Holder: Coronation Gardens Onwers Association | J3: Account Holder: Coronation Gardens Onwers Association | R3: Period: 2025-05-01 to 2025-05-31
R4: Currency: USD
A5: Account ID:58345 | J5: Account ID:58344
A6: Account Currency:USD | J6: Account Currency:ZIG
A7: Transaction Period:2025-05-01 - 2025-05-31 | J7: Transaction Period:2025-05-01 - 2025-05-31
R8: Property - Coronation Gardens, Greendale, Harare
A9: ID | B9: Date | C9: Description | D9: Debit | E9: Credit | F9: Balance | J9: ID | K9: Date | L9: Description | M9: Debit | N9: Credit | O9: Balance | R9: LeaseID | S9: Tenant | T9: Balance B/F | U9: Amount Charged | V9: Amount Due | W9: Amount Paid | X9: Carried Forward
C10: Balance brought forward | F10: -502.62 | L10: Balance brought forward | O10: 0 | R10: 5817 | S10: Agnes Furidze 1 Coronation | T10: -50 | U10: 50 | V10: 0 | W10: 0 | X10: 0
A11: 1372604 | B11: 45779 | C11: Journal ref-GATE REPAIRS | D11: 45 | F11: -547.62 | M11: 0 | N11: 0 | O11: 0 | R11: 5819 | S11: Eva Mutangadura 2 Coronation | T11: 0 | U11: 50 | V11: 50 | W11: 50 | X11: 0
A12: 1372857 | B12: 45783 | C12: Payment Leaseid-5831 Phillers Gwengo 14 Coronation Ref-LEVY - 14 CORONATION | E12: 50 | F12: -497.62 | R12: 5820 | S12: Kudzanayi Kachere 3 Coronation | T12: 0 | U12: 50 | V12: 50 | W12: 50 | X12: 0
A13: 1372860 | B13: 45783 | C13: Levy Commission Leaseid-5831 Ref-LEVY - 14 CORONATION | D13: 7.51 | F13: -505.13 | R13: 5821 | S13: Hebros Dubai 4 Coronation | T13: 65 | U13: 55 | V13: 120 | W13: 100 | X13: 20
A14: 1372864 | B14: 45783 | C14: Payment Leaseid-5827 Dorothy R. S Makoni 10 Coronation Ref-LEVY - 10 CORONATION | E14: 50 | F14: -455.13 | R14: 5822 | S14: Tatenda Ngowe 5 Coronation | T14: 50 | U14: 50 | V14: 100 | W14: 50 | X14: 50
A15: 1372867 | B15: 45783 | C15: Levy Commission Leaseid-5827 Ref-LEVY - 10 CORONATION | D15: 7.51 | F15: -462.64 | R15: 5823 | S15: Maud Silibaziso 6 Coronation | T15: 110 | U15: 55 | V15: 165 | W15: 97 | X15: 68
A16: 1372871 | B16: 45783 | C16: Payment Leaseid-5834 Margaret Mushayi 17 Coronation Ref-LEVY - 17 CORONATION | E16: 50 | F16: -412.64 | R16: 5824 | S16: Gibson Taruwinga 7 Coronation | T16: 0 | U16: 50 | V16: 50 | W16: 50 | X16: 0
A17: 1372874 | B17: 45783 | C17: Levy Commission Leaseid-5834 Ref-LEVY - 17 CORONATION | D17: 7.51 | F17: -420.15 | R17: 5825 | S17: Lody Machiwenyika 8 Coronation | T17: 100 | U17: 50 | V17: 150 | W17: 0 | X17: 150
A18: 1372878 | B18: 45783 | C18: Payment Leaseid-5828 Farai Chivaura 11 Coronation Ref-LEVY - 11 CORONATION | E18: 50 | F18: -370.15 | R18: 5826 | S18: Unit 9 Coronation Gardens | T18: 165 | U18: 55 | V18: 220 | W18: 220 | X18: 0
A19: 1372881 | B19: 45783 | C19: Levy Commission Leaseid-5828 Ref-LEVY - 11 CORONATION | D19: 7.51 | F19: -377.66 | R19: 5827 | S19: Dorothy R. S Makoni 10 Coronation | T19: 0 | U19: 50 | V19: 50 | W19: 50 | X19: 0
A20: 1372885 | B20: 45783 | C20: Payment Leaseid-5832 Toko Muodzi Ross 15 Coronation Gardens Ref-LEVY - 15 CORONATION | E20: 50 | F20: -327.66 | R20: 5828 | S20: Farai Chivaura 11 Coronation | T20: 20 | U20: 50 | V20: 70 | W20: 50 | X20: 20
A21: 1372888 | B21: 45783 | C21: Levy Commission Leaseid-5832 Ref-LEVY - 15 CORONATION | D21: 7.51 | F21: -335.17 | R21: 5829 | S21: Rose Chanakira 12 Coronation | T21: 50 | U21: 50 | V21: 100 | W21: 100 | X21: 0
A22: 1372892 | B22: 45783 | C22: Payment Leaseid-5830 Siketiwe Marima 13 Coronation Ref-LEVY - 13 CORONATION | E22: 50 | F22: -285.17 | R22: 5830 | S22: Siketiwe Marima 13 Coronation | T22: -50 | U22: 50 | V22: 0 | W22: 50 | X22: -50
A23: 1372895 | B23: 45783 | C23: Levy Commission Leaseid-5830 Ref-LEVY - 13 CORONATION | D23: 7.51 | F23: -292.68 | R23: 5831 | S23: Phillers Gwengo 14 Coronation | T23: 0 | U23: 50 | V23: 50 | W23: 50 | X23: 0
A24: 1372899 | B24: 45783 | C24: Payment Leaseid-5824 Gibson Taruwinga 7 Coronation Ref-LEVY - 7 CORONATION | E24: 50 | F24: -242.68 | R24: 5832 | S24: Toko Muodzi Ross 15 Coronation Gardens | T24: 0 | U24: 50 | V24: 50 | W24: 50 | X24: 0
A25: 1372902 | B25: 45783 | C25: Levy Commission Leaseid-5824 Ref-LEVY - 7 CORONATION | D25: 7.51 | F25: -250.19 | R25: 5833 | S25: Emeldah Paradza 16 Coronation | T25: 0 | U25: 50 | V25: 50 | W25: 50 | X25: 0
A26: 1372906 | B26: 45783 | C26: Payment Leaseid-5819 Eva Mutangadura 2 Coronation Ref-LEVY - 2 CORONATION | E26: 50 | F26: -200.19 | R26: 5834 | S26: Margaret Mushayi 17 Coronation | T26: 0 | U26: 50 | V26: 50 | W26: 50 | X26: 0
A27: 1372909 | B27: 45783 | C27: Levy Commission Leaseid-5819 Ref-LEVY - 2 CORONATION | D27: 7.51 | F27: -207.7 | T27: 460 | U27: 865 | V27: 1325 | W27: 1067 | X27: 258
A28: 1373217 | B28: 45783 | C28: Payment Leaseid-5833 Emeldah Paradza 16 Coronation Ref-LEVY-PARADZA E-16 CORONATION-ECOCASH-03/05/25 | E28: 50 | F28: -157.7 | X28: =X22 -> -50
A29: 1373220 | B29: 45783 | C29: Levy Commission Leaseid-5833 Ref-LEVY-PARADZA E-16 CORONATION-ECOCASH-03/05/25 | D29: 7.51 | F29: -165.21 | X29: =X28*-1 -> 50
A30: 1378069 | B30: 45783 | C30: Payment Leaseid-5829 Rose Chanakira 12 Coronation Ref-LEVY-CHANAKIRA R-12 CORONATION-ECOCASH-03/05/25 | E30: 100 | F30: -65.21 | X30: =X27+X29 -> 308
A31: 1378072 | B31: 45783 | C31: Levy Commission Leaseid-5829 Ref-LEVY-CHANAKIRA R-12 CORONATION-ECOCASH-03/05/25 | D31: 15.01 | F31: -80.22
A32: 1375930 | B32: 45785 | C32: Payment Ref-GATE REPAIRS | D32: 15 | F32: -95.22
A33: 1375645 | B33: 45786 | C33: Payment Leaseid-5826 Unit 9 Coronation Gardens Ref-LEVY-9 CORONATION-ECOCASH-07/05/25 | E33: 220 | F33: 124.78
A34: 1375648 | B34: 45786 | C34: Levy Commission Leaseid-5826 Ref-LEVY-9 CORONATION-ECOCASH-07/05/25 | D34: 33.02 | F34: 91.76
A35: 1376239 | B35: 45789 | C35: Payment Leaseid-5823 Maud Silibaziso 6 Coronation Ref-LEVY-SILIBAZISO M-6 CORONATION-ECOCASH-06/05/25 | E35: 97 | F35: 188.76
A36: 1376242 | B36: 45789 | C36: Levy Commission Leaseid-5823 Ref-LEVY-SILIBAZISO M-6 CORONATION-ECOCASH-06/05/25 | D36: 14.56 | F36: 174.2
A37: 1376269 | B37: 45789 | C37: Payment Leaseid-5822 Tatenda Ngowe 5 Coronation Ref-LEVY-NGOWE T-5 CORONATION-ECOCASH-06/05/25 | E37: 50 | F37: 224.2
A38: 1376272 | B38: 45789 | C38: Levy Commission Leaseid-5822 Ref-LEVY-NGOWE T-5 CORONATION-ECOCASH-06/05/25 | D38: 7.51 | F38: 216.69
A39: 1376297 | B39: 45789 | C39: Payment Leaseid-5820 Kudzanayi Kachere 3 Coronation Ref-LEVY-KACHERE K-3 CORONATION-TRANSFER-08/05/25 | E39: 50 | F39: 266.69
A40: 1376300 | B40: 45789 | C40: Levy Commission Leaseid-5820 Ref-LEVY-KACHERE K-3 CORONATION-TRANSFER-08/05/25 | D40: 7.51 | F40: 259.18
A41: 1377947 | B41: 45792 | C41: Payment Ref-ELECTRICALS FOR THE GATE | D41: 8 | F41: 251.18
A42: 1380083 | B42: 45804 | C42: Payment Ref-GATE REPAIRS | D42: 50 | F42: 201.18
A43: 1379945 | B43: 45805 | C43: Payment Leaseid-5821 Hebros Dubai 4 Coronation Ref-LEVY - 4 CORONATION | E43: 100 | F43: 301.18
A44: 1379948 | B44: 45805 | C44: Levy Commission Leaseid-5821 Ref-LEVY - 4 CORONATION | D44: 15.01 | F44: 286.17
A45: 1382718 | B45: 45807 | C45: Journal ref-STAFF SALARIES | D45: 543 | F45: -256.83
D46: 821.21 | E46: 1067 | F46: -256.83

Sheet April 25
A1: Statement | I1: Statement | Q1: Roll Over Summary
Q2: landlord - Coronation Gardens Onwers Association
A3: Account Holder: Coronation Gardens Onwers Association | I3: Account Holder: Coronation Gardens Onwers Association | Q3: Period: 2025-04-01 to 2025-04-30
Q4: Currency: USD
A5: Account ID:58345 | I5: Account ID:58344
A6: Account Currency:USD | I6: Account Currency:ZIG
A7: Transaction Period:2025-04-01 - 2025-04-30 | I7: Transaction Period:2025-04-01 - 2025-04-30
Q8: Property - Coronation Gardens, Greendale, Harare
A9: ID | B9: Date | C9: Description | D9: Debit | E9: Credit | F9: Balance | I9: ID | J9: Date | K9: Description | L9: Debit | M9: Credit | N9: Balance | Q9: LeaseID | R9: Tenant | S9: Balance B/F | T9: Amount Charged | U9: Amount Due | V9: Amount Paid | W9: Carried Forward
C10: Balance brought forward | F10: 525.99 | K10: Balance brought forward | N10: 0 | Q10: 5817 | R10: Agnes Furidze 1 Coronation | S10: 0 | T10: 50 | U10: 50 | V10: 100 | W10: -50
A11: 1363463 | B11: 45748 | C11: Payment Ref-STAFF SALARIES | D11: 543 | F11: -17.01 | L11: 0 | M11: 0 | N11: 0 | Q11: 5819 | R11: Eva Mutangadura 2 Coronation | S11: 0 | T11: 50 | U11: 50 | V11: 50 | W11: 0
A12: 1361544 | B12: 45749 | C12: Payment Leaseid-5834 Margaret Mushayi 17 Coronation Ref-LEVY - 17 CORONATION | E12: 50 | F12: -17.01 | Q12: 5820 | R12: Kudzanayi Kachere 3 Coronation | S12: 0 | T12: 50 | U12: 50 | V12: 50 | W12: 0
A13: 1361547 | B13: 45749 | C13: Levy Commission Leaseid-5834 Ref-LEVY - 17 CORONATION | D13: 7.51 | F13: -24.52 | Q13: 5821 | R13: Hebros Dubai 4 Coronation | S13: 10 | T13: 50 | U13: 60 | V13: 0 | W13: 60
A14: 1361551 | B14: 45749 | C14: Payment Leaseid-5831 Phillers Gwengo 14 Coronation Ref-LEVY - 14 CORONATION | E14: 50 | F14: 25.48 | Q14: 5822 | R14: Tatenda Ngowe 5 Coronation | S14: 0 | T14: 50 | U14: 50 | V14: 0 | W14: 50
A15: 1361554 | B15: 45749 | C15: Levy Commission Leaseid-5831 Ref-LEVY - 14 CORONATION | D15: 7.51 | F15: 17.97 | Q15: 5823 | R15: Maud Silibaziso 6 Coronation | S15: 55 | T15: 50 | U15: 105 | V15: 0 | W15: 105
A16: 1361558 | B16: 45749 | C16: Payment Leaseid-5832 Toko Muodzi Ross 15 Coronation Gardens Ref-LEVY - 15 CORONATION | E16: 50 | F16: 67.97 | Q16: 5824 | R16: Gibson Taruwinga 7 Coronation | S16: 0 | T16: 50 | U16: 50 | V16: 50 | W16: 0
A17: 1361561 | B17: 45749 | C17: Levy Commission Leaseid-5832 Ref-LEVY - 15 CORONATION | D17: 7.51 | F17: 60.46 | Q17: 5825 | R17: Lody Machiwenyika 8 Coronation | S17: 50 | T17: 50 | U17: 100 | V17: 0 | W17: 100
A18: 1361565 | B18: 45749 | C18: Payment Leaseid-5824 Gibson Taruwinga 7 Coronation Ref-LEVY - 7 CORONATION | E18: 50 | F18: 110.46 | Q18: 5826 | R18: Unit 9 Coronation Gardens | S18: 105 | T18: 50 | U18: 155 | V18: 0 | W18: 155
A19: 1361568 | B19: 45749 | C19: Levy Commission Leaseid-5824 Ref-LEVY - 7 CORONATION | D19: 7.51 | F19: 102.95 | Q19: 5827 | R19: Dorothy R. S Makoni 10 Coronation | S19: 0 | T19: 50 | U19: 50 | V19: 50 | W19: 0
A20: 1361572 | B20: 45749 | C20: Payment Leaseid-5819 Eva Mutangadura 2 Coronation Ref-LEVY - 2 CORONATION | E20: 50 | F20: 152.95 | Q20: 5828 | R20: Farai Chivaura 11 Coronation | S20: 20 | T20: 50 | U20: 70 | V20: 50 | W20: 20
A21: 1361575 | B21: 45749 | C21: Levy Commission Leaseid-5819 Ref-LEVY - 2 CORONATION | D21: 7.51 | F21: 145.44 | Q21: 5829 | R21: Rose Chanakira 12 Coronation | S21: 0 | T21: 50 | U21: 50 | V21: 0 | W21: 50
A22: 1361579 | B22: 45749 | C22: Payment Leaseid-5828 Farai Chivaura 11 Coronation Ref-LEVY - 11 CORONATION | E22: 50 | F22: 195.44 | Q22: 5830 | R22: Siketiwe Marima 13 Coronation | S22: -100 | T22: 50 | U22: -50 | V22: 0 | W22: -50
A23: 1361582 | B23: 45749 | C23: Levy Commission Leaseid-5828 Ref-LEVY - 11 CORONATION | D23: 7.51 | F23: 187.93 | Q23: 5831 | R23: Phillers Gwengo 14 Coronation | S23: 0 | T23: 50 | U23: 50 | V23: 50 | W23: 0
A24: 1362876 | B24: 45750 | C24: Payment Leaseid-5833 Emeldah Paradza 16 Coronation Ref-LEVY-PARADZA E-16 CORONATION-ECOCASH-02/04/25 | E24: 50 | F24: 237.93 | Q24: 5832 | R24: Toko Muodzi Ross 15 Coronation Gardens | S24: 0 | T24: 50 | U24: 50 | V24: 50 | W24: 0
A25: 1362879 | B25: 45750 | C25: Levy Commission Leaseid-5833 Ref-LEVY-PARADZA E-16 CORONATION-ECOCASH-02/04/25 | D25: 7.51 | F25: 230.42 | Q25: 5833 | R25: Emeldah Paradza 16 Coronation | S25: 0 | T25: 50 | U25: 50 | V25: 50 | W25: 0
A26: 1363724 | B26: 45751 | C26: Payment Leaseid-5817 Agnes Furidze 1 Coronation Ref-LEVY-FURIDZE A-1 CORONATION-TRANSFER-31/03/25 | E26: 50 | F26: 280.42 | Q26: 5834 | R26: Margaret Mushayi 17 Coronation | S26: 0 | T26: 50 | U26: 50 | V26: 50 | W26: 0
A27: 1363727 | B27: 45751 | C27: Levy Commission Leaseid-5817 Ref-LEVY-FURIDZE A-1 CORONATION-TRANSFER-31/03/25 | D27: 7.51 | F27: 272.91 | S27: 140 | T27: 850 | U27: 990 | V27: 550 | W27: 440
A28: 1365440 | B28: 45755 | C28: Payment Leaseid-5820 Kudzanayi Kachere 3 Coronation Ref-LEVY-KACHERE K-3 CORONATION-TRANSFER-04/04/25 | E28: 50 | F28: 322.91 | W28: =W10+W22 -> -100
A29: 1365443 | B29: 45755 | C29: Levy Commission Leaseid-5820 Ref-LEVY-KACHERE K-3 CORONATION-TRANSFER-04/04/25 | D29: 7.51 | F29: 315.4 | W29: =W28*-1 -> 100
A30: 1366918 | B30: 45756 | C30: Payment Ref-GATE MOTOR BALANCE | D30: 275 | F30: 40.4 | W30: =W29+W27 -> 540
A31: 1367023 | B31: 45757 | C31: Payment Leaseid-5827 Dorothy R. S Makoni 10 Coronation Ref-LEVY-MAKONI D-10 CORONATION-ECOCASH-09/04/25 | E31: 50 | F31: 90.4
A32: 1367026 | B32: 45757 | C32: Levy Commission Leaseid-5827 Ref-LEVY-MAKONI D-10 CORONATION-ECOCASH-09/04/25 | D32: 7.51 | F32: 82.89
A33: 1369500 | B33: 45772 | C33: Payment Leaseid-5817 Agnes Furidze 1 Coronation Ref-LEVY-FURIDZE A-1 CORONATION-TRANSFER-24/04/25 | E33: 50 | F33: 132.89
A34: 1369503 | B34: 45772 | C34: Levy Commission Leaseid-5817 Ref-LEVY-FURIDZE A-1 CORONATION-TRANSFER-24/04/25 | D34: 7.51 | F34: 125.38
A35: 1369876 | B35: 45772 | C35: Payment Ref-UPPER MANYAME | D35: 80 | F35: 45.38
A36: 1370678 | B36: 45777 | C36: Journal ref-STAFF SALARIES | D36: 543 | F36: -497.62
A37: 1371978 | B37: 45777 | C37: Journal ref-MURARA BROOM | D37: 5 | F37: -502.62
D38: 1528.61 | E38: 550 | F38: -502.62

Sheet MARCH 25
A1: Statement | I1: Statement | Q1: Roll Over Summary
Q2: landlord - Coronation Gardens Onwers Association
A3: Account Holder: Coronation Gardens Onwers Association | I3: Account Holder: Coronation Gardens Onwers Association | Q3: Period: 2025-03-01 to 2025-03-31
Q4: Currency: USD
A5: Account ID:58345 | I5: Account ID:58344
A6: Account Currency:USD | I6: Account Currency:ZIG
A7: Transaction Period:2025-03-01 - 2025-03-31 | I7: Transaction Period:2025-03-01 - 2025-03-31
Q8: Property - Coronation Gardens, Greendale, Harare
A9: ID | B9: Date | C9: Description | D9: Debit | E9: Credit | F9: Balance | I9: ID | J9: Date | K9: Description | L9: Debit | M9: Credit | N9: Balance | Q9: LeaseID | R9: Tenant | S9: Balance B/F | T9: Amount Charged | U9: Amount Due | V9: Amount Paid | W9: Carried Forward
C10: Balance brought forward | F10: 204.15 | K10: Balance brought forward | N10: 0 | Q10: 5817 | R10: Agnes Furidze 1 Coronation | S10: 0 | T10: 50 | U10: 50 | V10: 50 | W10: 0
A11: 1354045 | B11: 45720 | C11: Payment Leaseid-5821 Hebros Dubai 4 Coronation Ref-LEVY - 4 CORONATION | E11: 150 | F11: 354.15 | L11: 0 | M11: 0 | N11: 0 | Q11: 5819 | R11: Eva Mutangadura 2 Coronation | S11: 0 | T11: 50 | U11: 50 | V11: 50 | W11: 0
A12: 1354048 | B12: 45720 | C12: Levy Commission Leaseid-5821 Ref-LEVY - 4 CORONATION | D12: 22.52 | F12: 331.63 | Q12: 5820 | R12: Kudzanayi Kachere 3 Coronation | S12: -50 | T12: 50 | U12: 0 | V12: 0 | W12: 0
A13: 1354094 | B13: 45720 | C13: Payment Leaseid-5834 Margaret Mushayi 17 Coronation Ref-LEVY - 17 CORONATION | E13: 50 | F13: 381.63 | Q13: 5821 | R13: Hebros Dubai 4 Coronation | S13: 110 | T13: 50 | U13: 160 | V13: 150 | W13: 10
A14: 1354097 | B14: 45720 | C14: Levy Commission Leaseid-5834 Ref-LEVY - 17 CORONATION | D14: 7.51 | F14: 374.12 | Q14: 5822 | R14: Tatenda Ngowe 5 Coronation | S14: 55 | T14: 50 | U14: 105 | V14: 105 | W14: 0
A15: 1354101 | B15: 45720 | C15: Payment Leaseid-5828 Farai Chivaura 11 Coronation Ref-LEVY - 11 CORONATION | E15: 50 | F15: 424.12 | Q15: 5823 | R15: Maud Silibaziso 6 Coronation | S15: 55 | T15: 50 | U15: 105 | V15: 50 | W15: 55
A16: 1354104 | B16: 45720 | C16: Levy Commission Leaseid-5828 Ref-LEVY - 11 CORONATION | D16: 7.51 | F16: 416.61 | Q16: 5824 | R16: Gibson Taruwinga 7 Coronation | S16: 55 | T16: 50 | U16: 105 | V16: 105 | W16: 0
A17: 1354108 | B17: 45720 | C17: Payment Leaseid-5827 Dorothy R. S Makoni 10 Coronation Ref-LEVY - 10 CORONATION | E17: 50 | F17: 466.61 | Q17: 5825 | R17: Lody Machiwenyika 8 Coronation | S17: 0 | T17: 50 | U17: 50 | V17: 0 | W17: 50
A18: 1354111 | B18: 45720 | C18: Levy Commission Leaseid-5827 Ref-LEVY - 10 CORONATION | D18: 7.51 | F18: 459.1 | Q18: 5826 | R18: Unit 9 Coronation Gardens | S18: 55 | T18: 50 | U18: 105 | V18: 0 | W18: 105
A19: 1354115 | B19: 45720 | C19: Payment Leaseid-5822 Tatenda Ngowe 5 Coronation Ref-LEVY - 5 CORONATION | E19: 50 | F19: 509.1 | Q19: 5827 | R19: Dorothy R. S Makoni 10 Coronation | S19: 0 | T19: 50 | U19: 50 | V19: 50 | W19: 0
A20: 1354118 | B20: 45720 | C20: Levy Commission Leaseid-5822 Ref-LEVY - 5 CORONATION | D20: 7.51 | F20: 501.59 | Q20: 5828 | R20: Farai Chivaura 11 Coronation | S20: 20 | T20: 50 | U20: 70 | V20: 50 | W20: 20
A21: 1354122 | B21: 45720 | C21: Payment Leaseid-5829 Rose Chanakira 12 Coronation Ref-LEVY - 12 CORONATION | E21: 50 | F21: 551.59 | Q21: 5829 | R21: Rose Chanakira 12 Coronation | S21: 0 | T21: 50 | U21: 50 | V21: 50 | W21: 0
A22: 1354125 | B22: 45720 | C22: Levy Commission Leaseid-5829 Ref-LEVY - 12 CORONATION | D22: 7.51 | F22: 544.08 | Q22: 5830 | R22: Siketiwe Marima 13 Coronation | S22: -150 | T22: 50 | U22: -100 | V22: 0 | W22: -100
A23: 1354129 | B23: 45720 | C23: Payment Leaseid-5832 Toko Muodzi Ross 15 Coronation Gardens Ref-LEVY - 15 CORONATION | E23: 50 | F23: 594.08 | Q23: 5831 | R23: Phillers Gwengo 14 Coronation | S23: 0 | T23: 50 | U23: 50 | V23: 50 | W23: 0
A24: 1354132 | B24: 45720 | C24: Levy Commission Leaseid-5832 Ref-LEVY - 15 CORONATION | D24: 7.51 | F24: 586.57 | Q24: 5832 | R24: Toko Muodzi Ross 15 Coronation Gardens | S24: 0 | T24: 50 | U24: 50 | V24: 50 | W24: 0
A25: 1354136 | B25: 45720 | C25: Payment Leaseid-5822 Tatenda Ngowe 5 Coronation Ref-LEVY - 5 CORONATION | E25: 55 | F25: 641.57 | Q25: 5833 | R25: Emeldah Paradza 16 Coronation | S25: 0 | T25: 50 | U25: 50 | V25: 50 | W25: 0
A26: 1354139 | B26: 45720 | C26: Levy Commission Leaseid-5822 Ref-LEVY - 5 CORONATION | D26: 8.26 | F26: 633.31 | Q26: 5834 | R26: Margaret Mushayi 17 Coronation | S26: 0 | T26: 50 | U26: 50 | V26: 50 | W26: 0
A27: 1354143 | B27: 45720 | C27: Payment Leaseid-5831 Phillers Gwengo 14 Coronation Ref-LEVY - 14 CORONATION | E27: 50 | F27: 683.31 | S27: 150 | T27: 850 | U27: 1000 | V27: 860 | W27: 140
A28: 1354146 | B28: 45720 | C28: Levy Commission Leaseid-5831 Ref-LEVY - 14 CORONATION | D28: 7.51 | F28: 675.8 | W28: =W22 -> -100
A29: 1354150 | B29: 45720 | C29: Payment Leaseid-5824 Gibson Taruwinga 7 Coronation Ref-LEVY - 7 CORONATION | E29: 50 | F29: 725.8 | W29: =W28*-1 -> 100
A30: 1354153 | B30: 45720 | C30: Levy Commission Leaseid-5824 Ref-LEVY - 7 CORONATION | D30: 7.51 | F30: 718.29 | W30: =W27+W29 -> 240
A31: 1354157 | B31: 45720 | C31: Payment Leaseid-5824 Gibson Taruwinga 7 Coronation Ref-INTEREST - 7 CORONATION | E31: 5 | F31: 723.29
A32: 1354160 | B32: 45720 | C32: Levy Commission Leaseid-5824 Ref-INTEREST - 7 CORONATION | D32: 0.75 | F32: 722.54
A33: 1354164 | B33: 45720 | C33: Payment Leaseid-5823 Maud Silibaziso 6 Coronation Ref-LEVY - 6 CORONATION | E33: 50 | F33: 772.54
A34: 1354167 | B34: 45720 | C34: Levy Commission Leaseid-5823 Ref-LEVY - 6 CORONATION | D34: 7.51 | F34: 765.03
A35: 1354171 | B35: 45720 | C35: Payment Leaseid-5819 Eva Mutangadura 2 Coronation Ref-LEVY - 2 CORONATION | E35: 50 | F35: 815.03
A36: 1354174 | B36: 45720 | C36: Levy Commission Leaseid-5819 Ref-LEVY - 2 CORONATION | D36: 7.51 | F36: 807.52
A37: 1358079 | B37: 45722 | C37: Payment Ref-PLUMBING WORKS | D37: 30 | F37: 777.52
A38: 1358081 | B38: 45722 | C38: Payment Ref-GATE MOTOR DEPOSIT | D38: 276 | F38: 501.52
A39: 1355691 | B39: 45723 | C39: Payment Leaseid-5824 Gibson Taruwinga 7 Coronation Ref-LEVY-TARUWINGA G-7 CORONATION-TRANSFER-11/02/25 | E39: 50 | F39: 551.52
A40: 1355694 | B40: 45723 | C40: Levy Commission Leaseid-5824 Ref-LEVY-TARUWINGA G-7 CORONATION-TRANSFER-11/02/25 | D40: 7.51 | F40: 544.01
A41: 1355711 | B41: 45723 | C41: Payment Leaseid-5817 Agnes Furidze 1 Coronation Ref-LEVY-FURIDZE A-1 CORONATION-TRANSFER-04/03/25 | E41: 50 | F41: 594.01
A42: 1355714 | B42: 45723 | C42: Levy Commission Leaseid-5817 Ref-LEVY-FURIDZE A-1 CORONATION-TRANSFER-04/03/25 | D42: 7.51 | F42: 586.5
A43: 1356588 | B43: 45726 | C43: Payment Leaseid-5833 Emeldah Paradza 16 Coronation Ref-LEVY-PARADZA E-16 CORONATION-ECOCASH-04/03/25 | E43: 50 | F43: 636.5
A44: 1356591 | B44: 45726 | C44: Levy Commission Leaseid-5833 Ref-LEVY-PARADZA E-16 CORONATION-ECOCASH-04/03/25 | D44: 7.51 | F44: 628.99
A45: 1358168 | B45: 45727 | C45: Payment Ref-WORKSUITS PURCHASE | D45: 13 | F45: 615.99
A46: 1359182 | B46: 45735 | C46: Payment Ref-COMPLEX SIGNAGE | D46: 140 | F46: 475.99
D47: 588.16 | E47: 860 | F47: 475.99

Sheet FEB
A1: Statement | I1: Statement | Q1: Roll Over Summary
Q2: landlord - Coronation Gardens Onwers Association
A3: Account Holder: Coronation Gardens Onwers Association | I3: Account Holder: Coronation Gardens Onwers Association | Q3: Period: 2025-02-01 to 2025-02-28
Q4: Currency: USD
A5: Account ID:58345 | I5: Account ID:58344
A6: Account Currency:USD | I6: Account Currency:ZIG
A7: Transaction Period:2025-02-01 - 2025-02-28 | I7: Transaction Period:2025-02-01 - 2025-02-28
Q8: Property - Coronation Gardens, Greendale, Harare
A9: ID | B9: Date | C9: Description | D9: Debit | E9: Credit | F9: Balance | I9: ID | J9: Date | K9: Description | L9: Debit | M9: Credit | N9: Balance | Q9: LeaseID | R9: Tenant | S9: Balance B/F | T9: Amount Charged | U9: Amount Due | V9: Amount Paid | W9: Carried Forward
C10: Balance brought forward | F10: 4.81 | G10: =F10 -> 4.81 | K10: Balance brought forward | N10: 0 | Q10: 5817 | R10: Agnes Furidze 1 Coronation | S10: 0 | T10: 50 | U10: 50 | V10: 50 | W10: 0
A11: 1349605 | B11: 45691 | C11: Payment Leaseid-5832 Toko Muodzi Ross 15 Coronation Gardens Ref-LEVY - 15 CORONATION | E11: 50 | F11: 54.81 | G11: =G10+E11-D11 -> 54.81 | L11: 0 | M11: 0 | N11: 0 | Q11: 5819 | R11: Eva Mutangadura 2 Coronation | S11: 0 | T11: 50 | U11: 50 | V11: 50 | W11: 0
A12: 1349608 | B12: 45691 | C12: Levy Commission Leaseid-5832 Ref-LEVY - 15 CORONATION | D12: 7.51 | F12: 47.3 | G12: =G11+E12-D12 -> 47.3 | Q12: 5820 | R12: Kudzanayi Kachere 3 Coronation | S12: 250 | T12: 50 | U12: 300 | V12: 350 | W12: -50
A13: 1344234 | B13: 45692 | C13: Payment Leaseid-5827 Dorothy R. S Makoni 10 Coronation Ref-LEVY 10 CORONATION MAKONI CASH | E13: 50 | F13: 97.3 | G13: =G12+E13-D13 -> 97.3 | Q13: 5821 | R13: Hebros Dubai 4 Coronation | S13: 50 | T13: 60 | U13: 110 | V13: 0 | W13: 110
A14: 1344237 | B14: 45692 | C14: Levy Commission Leaseid-5827 Ref-LEVY 10 CORONATION MAKONI CASH | D14: 7.51 | F14: 89.79 | G14: =G13+E14-D14 -> 89.79 | Q14: 5822 | R14: Tatenda Ngowe 5 Coronation | S14: 0 | T14: 55 | U14: 55 | V14: 0 | W14: 55
A15: 1344255 | B15: 45692 | C15: Payment Leaseid-5834 Margaret Mushayi 17 Coronation Ref-LEVY 17 CORONATION MUSHAYI CASH | E15: 50 | F15: 139.79 | G15: =G14+E15-D15 -> 139.79 | Q15: 5823 | R15: Maud Silibaziso 6 Coronation | S15: 0 | T15: 55 | U15: 55 | V15: 0 | W15: 55
A16: 1344258 | B16: 45692 | C16: Levy Commission Leaseid-5834 Ref-LEVY 17 CORONATION MUSHAYI CASH | D16: 7.51 | F16: 132.28 | G16: =G15+E16-D16 -> 132.28 | Q16: 5824 | R16: Gibson Taruwinga 7 Coronation | S16: 0 | T16: 55 | U16: 55 | V16: 0 | W16: 55
A17: 1344262 | B17: 45692 | C17: Payment Leaseid-5833 Emeldah Paradza 16 Coronation Ref-LEVY 16 CORONATION PARADZA CASH | E17: 50 | F17: 182.28 | G17: =G16+E17-D17 -> 182.28 | Q17: 5825 | R17: Lody Machiwenyika 8 Coronation | S17: 100 | T17: 50 | U17: 150 | V17: 150 | W17: 0
A18: 1344265 | B18: 45692 | C18: Levy Commission Leaseid-5833 Ref-LEVY 16 CORONATION PARADZA CASH | D18: 7.51 | F18: 174.77 | G18: =G17+E18-D18 -> 174.77 | Q18: 5826 | R18: Unit 9 Coronation Gardens | S18: 50 | T18: 55 | U18: 105 | V18: 50 | W18: 55
A19: 1344269 | B19: 45692 | C19: Payment Leaseid-5829 Rose Chanakira 12 Coronation Ref-LEVY CHANAKIRA 12 CORONATION CASH | E19: 50 | F19: 224.77 | G19: =G18+E19-D19 -> 224.77 | Q19: 5827 | R19: Dorothy R. S Makoni 10 Coronation | S19: 0 | T19: 50 | U19: 50 | V19: 50 | W19: 0
A20: 1344272 | B20: 45692 | C20: Levy Commission Leaseid-5829 Ref-LEVY CHANAKIRA 12 CORONATION CASH | D20: 7.51 | F20: 217.26 | G20: =G19+E20-D20 -> 217.26 | Q20: 5828 | R20: Farai Chivaura 11 Coronation | S20: -30 | T20: 50 | U20: 20 | V20: 0 | W20: 20
A21: 1344283 | B21: 45692 | C21: Payment Leaseid-5830 Siketiwe Marima 13 Coronation Ref-LEVY 13 CORONATION SIKETIWE CASH | E21: 100 | F21: 317.26 | G21: =G20+E21-D21 -> 317.26 | Q21: 5829 | R21: Rose Chanakira 12 Coronation | S21: 0 | T21: 50 | U21: 50 | V21: 50 | W21: 0
A22: 1344286 | B22: 45692 | C22: Levy Commission Leaseid-5830 Ref-LEVY 13 CORONATION SIKETIWE CASH | D22: 15.01 | F22: 302.25 | G22: =G21+E22-D22 -> 302.25 | Q22: 5830 | R22: Siketiwe Marima 13 Coronation | S22: -100 | T22: 50 | U22: -50 | V22: 100 | W22: -150
A23: 1344290 | B23: 45692 | C23: Payment Leaseid-5831 Phillers Gwengo 14 Coronation Ref-LEVY 14 CORONATION GWENGO CASH | E23: 50 | F23: 352.25 | G23: =G22+E23-D23 -> 352.25 | Q23: 5831 | R23: Phillers Gwengo 14 Coronation | S23: 0 | T23: 50 | U23: 50 | V23: 50 | W23: 0
A24: 1344293 | B24: 45692 | C24: Levy Commission Leaseid-5831 Ref-LEVY 14 CORONATION GWENGO CASH | D24: 7.51 | F24: 344.74 | G24: =G23+E24-D24 -> 344.74 | Q24: 5832 | R24: Toko Muodzi Ross 15 Coronation Gardens | S24: 0 | T24: 50 | U24: 50 | V24: 50 | W24: 0
A25: 1344297 | B25: 45692 | C25: Payment Leaseid-5826 Unit 9 Coronation Gardens Ref-LEVY 9 CORONATION CASH | E25: 50 | F25: 394.74 | G25: =G24+E25-D25 -> 394.74 | Q25: 5833 | R25: Emeldah Paradza 16 Coronation | S25: 0 | T25: 50 | U25: 50 | V25: 50 | W25: 0
A26: 1344300 | B26: 45692 | C26: Levy Commission Leaseid-5826 Ref-LEVY 9 CORONATION CASH | D26: 7.51 | F26: 387.23 | G26: =G25+E26-D26 -> 387.23 | Q26: 5834 | R26: Margaret Mushayi 17 Coronation | S26: 0 | T26: 50 | U26: 50 | V26: 50 | W26: 0
A27: 1344304 | B27: 45692 | C27: Payment Leaseid-5819 Eva Mutangadura 2 Coronation Ref-LEVY 2 CORONATION EVA CASH | E27: 50 | F27: 437.23 | G27: =G26+E27-D27 -> 437.23 | S27: 320 | T27: 880 | U27: 1200 | V27: 1050 | W27: 150
A28: 1344307 | B28: 45692 | C28: Levy Commission Leaseid-5819 Ref-LEVY 2 CORONATION EVA CASH | D28: 7.51 | F28: 429.72 | G28: =G27+E28-D28 -> 429.72 | W28: =W12+W22 -> -200
A29: 1346552 | B29: 45698 | C29: Payment Leaseid-5817 Agnes Furidze 1 Coronation Ref-LEVY-FURIDZE A-1 CORONATION-TRANSFER-04/02/25 | E29: 50 | F29: 479.72 | G29: =G28+E29-D29 -> 479.72 | W29: =W28*-1 -> 200
A30: 1346555 | B30: 45698 | C30: Levy Commission Leaseid-5817 Ref-LEVY-FURIDZE A-1 CORONATION-TRANSFER-04/02/25 | D30: 7.51 | F30: 472.21 | G30: =G29+E30-D30 -> 472.21 | W30: =W29+W27 -> 350
A31: 1347609 | B31: 45700 | C31: Payment Leaseid-5820 Kudzanayi Kachere 3 Coronation Ref-LEVY-KACHERE K-3 CORONATION-TRANSFER-30/01/25 | E31: 50 | F31: 522.21 | G31: =G30+E31-D31 -> 522.21
A32: 1347612 | B32: 45700 | C32: Levy Commission Leaseid-5820 Ref-LEVY-KACHERE K-3 CORONATION-TRANSFER-30/01/25 | D32: 7.51 | F32: 514.7 | G32: =G31+E32-D32 -> 514.7
A33: 1351050 | B33: 45708 | C33: Payment Leaseid-5825 Lody Machiwenyika 8 Coronation Ref-LEVY - 8 CORONATION | E33: 150 | F33: 664.7 | G33: =G32+E33-D33 -> 664.7
A34: 1351053 | B34: 45708 | C34: Levy Commission Leaseid-5825 Ref-LEVY - 8 CORONATION | D34: 22.52 | F34: 642.18 | G34: =G33+E34-D34 -> 642.18
A35: 1350585 | B35: 45714 | C35: Payment Leaseid-5820 Kudzanayi Kachere 3 Coronation Ref-LEVY-KACHERE K-3 CORONATION-TRANSFER-22/02/25 | E35: 250 | F35: 892.18 | G35: =G34+E35-D35 -> 892.18
A36: 1350588 | B36: 45714 | C36: Levy Commission Leaseid-5820 Ref-LEVY-KACHERE K-3 CORONATION-TRANSFER-22/02/25 | D36: 37.52 | F36: 854.66 | G36: =G35+E36-D36 -> 854.66
A37: 1350592 | B37: 45714 | C37: Payment Leaseid-5820 Kudzanayi Kachere 3 Coronation Ref-LEVY-KACHERE K-3 CORONATION-TRANSFER-25/02/25 | E37: 50 | F37: 904.66 | G37: =G36+E37-D37 -> 904.66
A38: 1350595 | B38: 45714 | C38: Levy Commission Leaseid-5820 Ref-LEVY-KACHERE K-3 CORONATION-TRANSFER-25/02/25 | D38: 7.51 | F38: 897.15 | G38: =G37+E38-D38 -> 897.15
A39: 1353512 | B39: 45715 | C39: Payment Ref-ZESA PURCHASE-DEC-JAN-FEB | D39: 150 | F39: 747.15 | G39: =G38+E39-D39 -> 747.15
A40: 1355029 | B40: 45716 | C40: Payment Ref-WAGES FEB | D40: 543 | F40: 354.15 | G40: =G39+E40-D40 -> 204.15
D41: 850.66 | E41: 1050 | F41: 354.15

Sheet January
A1: Statement | J1: Statement | R1: Roll Over Summary
R2: landlord - Coronation Gardens Onwers Association
A3: Account Holder: Coronation Gardens Onwers Association | J3: Account Holder: Coronation Gardens Onwers Association | R3: Period: 2025-01-01 to 2025-01-31
R4: Currency: USD
A5: Account ID:58345 | J5: Account ID:58344
A6: Account Currency:USD | J6: Account Currency:ZIG
A7: Transaction Period:2025-01-01 - 2025-01-31 | J7: Transaction Period:2025-01-01 - 2025-01-31
R8: Property - Coronation Gardens, Greendale, Harare
A9: ID | B9: Date | C9: Description | D9: Debit | E9: Credit | F9: Balance | J9: ID | K9: Date | L9: Description | M9: Debit | N9: Credit | O9: Balance | R9: LeaseID | S9: Tenant | T9: Balance B/F | U9: Amount Charged | V9: Amount Due | W9: Amount Paid | X9: Carried Forward
C10: Balance brought forward | F10: 14.55 | L10: Balance brought forward | O10: 0 | R10: 5817 | S10: Agnes Furidze 1 Coronation | T10: 0 | U10: 50 | V10: 50 | W10: 50 | X10: 0
A11: 1331380 | B11: 45663 | C11: Payment Leaseid-5827 Dorothy R. S Makoni 10 Coronation Ref-LEVY - 10 CORONATION | E11: 50 | F11: 64.55 | M11: 0 | N11: 0 | O11: 0 | R11: 5819 | S11: Eva Mutangadura 2 Coronation | T11: 0 | U11: 50 | V11: 50 | W11: 50 | X11: 0
A12: 1331383 | B12: 45663 | C12: Levy Commission Leaseid-5827 Ref-LEVY - 10 CORONATION | D12: 7.51 | F12: 57.04 | R12: 5820 | S12: Kudzanayi Kachere 3 Coronation | T12: 200 | U12: 50 | V12: 250 | W12: 0 | X12: 250
A13: 1331387 | B13: 45663 | C13: Payment Leaseid-5828 Farai Chivaura 11 Coronation Ref-LEVY - 11 CORONATION | E13: 50 | F13: 107.04 | R13: 5821 | S13: Hebros Dubai 4 Coronation | T13: 0 | U13: 50 | V13: 50 | W13: 0 | X13: 50
A14: 1331390 | B14: 45663 | C14: Levy Commission Leaseid-5828 Ref-LEVY - 11 CORONATION | D14: 7.51 | F14: 99.53 | R14: 5822 | S14: Tatenda Ngowe 5 Coronation | T14: -50 | U14: 50 | V14: 0 | W14: 0 | X14: 0
A15: 1331394 | B15: 45663 | C15: Payment Leaseid-5829 Rose Chanakira 12 Coronation Ref-LEVY - 12 CORONATION | E15: 50 | F15: 149.53 | R15: 5823 | S15: Maud Silibaziso 6 Coronation | T15: -50 | U15: 50 | V15: 0 | W15: 0 | X15: 0
A16: 1331397 | B16: 45663 | C16: Levy Commission Leaseid-5829 Ref-LEVY - 12 CORONATION | D16: 7.51 | F16: 142.02 | R16: 5824 | S16: Gibson Taruwinga 7 Coronation | T16: 0 | U16: 50 | V16: 50 | W16: 50 | X16: 0
A17: 1331401 | B17: 45663 | C17: Payment Leaseid-5832 Toko Muodzi Ross 15 Coronation Gardens Ref-LEVY - 15 CORONATION | E17: 50 | F17: 192.02 | R17: 5825 | S17: Lody Machiwenyika 8 Coronation | T17: 50 | U17: 50 | V17: 100 | W17: 0 | X17: 100
A18: 1331404 | B18: 45663 | C18: Levy Commission Leaseid-5832 Ref-LEVY - 15 CORONATION | D18: 7.51 | F18: 184.51 | R18: 5826 | S18: Unit 9 Coronation Gardens | T18: 50 | U18: 50 | V18: 100 | W18: 50 | X18: 50
A19: 1331408 | B19: 45663 | C19: Payment Leaseid-5831 Phillers Gwengo 14 Coronation Ref-LEVY - 14 CORONATION | E19: 50 | F19: 234.51 | R19: 5827 | S19: Dorothy R. S Makoni 10 Coronation | T19: 0 | U19: 50 | V19: 50 | W19: 50 | X19: 0
A20: 1331411 | B20: 45663 | C20: Levy Commission Leaseid-5831 Ref-LEVY - 14 CORONATION | D20: 7.51 | F20: 227 | R20: 5828 | S20: Farai Chivaura 11 Coronation | T20: 100 | U20: 50 | V20: 150 | W20: 180 | X20: -30
A21: 1331415 | B21: 45663 | C21: Payment Leaseid-5830 Siketiwe Marima 13 Coronation Ref-LEVY - 13 CORONATION | E21: 100 | F21: 327 | R21: 5829 | S21: Rose Chanakira 12 Coronation | T21: 0 | U21: 50 | V21: 50 | W21: 50 | X21: 0
A22: 1331418 | B22: 45663 | C22: Levy Commission Leaseid-5830 Ref-LEVY - 13 CORONATION | D22: 15.01 | F22: 311.99 | R22: 5830 | S22: Siketiwe Marima 13 Coronation | T22: -50 | U22: 50 | V22: 0 | W22: 100 | X22: -100
A23: 1331422 | B23: 45663 | C23: Payment Leaseid-5824 Gibson Taruwinga 7 Coronation Ref-LEVY - 7 CORONATION | E23: 50 | F23: 361.99 | R23: 5831 | S23: Phillers Gwengo 14 Coronation | T23: 0 | U23: 50 | V23: 50 | W23: 50 | X23: 0
A24: 1331425 | B24: 45663 | C24: Levy Commission Leaseid-5824 Ref-LEVY - 7 CORONATION | D24: 7.51 | F24: 354.48 | R24: 5832 | S24: Toko Muodzi Ross 15 Coronation Gardens | T24: 0 | U24: 50 | V24: 50 | W24: 50 | X24: 0
A25: 1331429 | B25: 45663 | C25: Payment Leaseid-5826 Unit 9 Coronation Gardens Ref-LEVY - 9 CORONATION | E25: 50 | F25: 404.48 | R25: 5833 | S25: Emeldah Paradza 16 Coronation | T25: 0 | U25: 50 | V25: 50 | W25: 50 | X25: 0
A26: 1331432 | B26: 45663 | C26: Levy Commission Leaseid-5826 Ref-LEVY - 9 CORONATION | D26: 7.51 | F26: 396.97 | R26: 5834 | S26: Margaret Mushayi 17 Coronation | T26: -50 | U26: 50 | V26: 0 | W26: 0 | X26: 0
A27: 1331436 | B27: 45663 | C27: Payment Leaseid-5819 Eva Mutangadura 2 Coronation Ref-LEVY - 2 CORONATION | E27: 50 | F27: 446.97 | T27: 200 | U27: 850 | V27: 1050 | W27: 730 | X27: 320
A28: 1331439 | B28: 45663 | C28: Levy Commission Leaseid-5819 Ref-LEVY - 2 CORONATION | D28: 7.51 | F28: 439.46 | X28: =X20+X22 -> -130
A29: 1331443 | B29: 45663 | C29: Payment Leaseid-5833 Emeldah Paradza 16 Coronation Ref-LEVY - 16 CORONATION | E29: 50 | F29: 489.46 | X29: =X28*-1 -> 130
A30: 1331446 | B30: 45663 | C30: Levy Commission Leaseid-5833 Ref-LEVY - 16 CORONATION | D30: 7.51 | F30: 481.95 | X30: =X29+X27 -> 450
A31: 1333177 | B31: 45666 | C31: Payment Leaseid-5817 Agnes Furidze 1 Coronation Ref-LEVY-FURIDZE A-1 CORONATION-TRANSFER-03/01/25 | E31: 50 | F31: 531.95
A32: 1333180 | B32: 45666 | C32: Levy Commission Leaseid-5817 Ref-LEVY-FURIDZE A-1 CORONATION-TRANSFER-03/01/25 | D32: 7.51 | F32: 524.44
A33: 1338666 | B33: 45678 | C33: Payment Ref-GATE REPAIRS | D33: 50 | F33: 474.44
A34: 1340074 | B34: 45678 | C34: Payment Leaseid-5828 Farai Chivaura 11 Coronation Ref-LEVY - 11 CORONATION | E34: 50 | F34: 524.44
A35: 1340077 | B35: 45678 | C35: Levy Commission Leaseid-5828 Ref-LEVY - 11 CORONATION | D35: 7.51 | F35: 516.93
A36: 1339869 | B36: 45681 | C36: Payment Ref-PLUMBING NON BOREHOLE WORKING | D36: 80 | F36: 436.93
A37: 1340067 | B37: 45681 | C37: Payment Leaseid-5828 Farai Chivaura 11 Coronation Ref-LEVY - 11 CORONATION | E37: 80 | F37: 516.93
A38: 1340070 | B38: 45681 | C38: Levy Commission Leaseid-5828 Ref-LEVY - 11 CORONATION | D38: 12.01 | F38: 504.92
A39: 1340738 | B39: 45688 | C39: Payment Ref-PAYROLL LICENSE FEES | D39: 34.11 | F39: 470.81
A40: 1343909 | B40: 45688 | C40: Payment Ref-STAFF SALARIES | D40: 456 | F40: 14.81
A41: 1344326 | B41: 45688 | C41: Payment Ref-PURCHASE OF BROOMS & MOPS | D41: 10 | F41: 4.81
D42: 739.74 | E42: 730 | F42: 4.81

Sheet OCtober
A1: Statement | J1: Statement | R1: Roll Over Summary
R2: landlord - Coronation Gardens Onwers Association
A3: Account Holder: Coronation Gardens Onwers Association | J3: Account Holder: Coronation Gardens Onwers Association | R3: Period: 2024-10-01 to 2024-10-31
R4: Currency: USD
A5: Account ID:58345 | J5: Account ID:58344
A6: Account Currency:USD | J6: Account Currency:ZIG
A7: Transaction Period:2024-10-01 - 2024-10-31 | J7: Transaction Period:2024-10-01 - 2024-10-31
R8: Property - Coronation Gardens, Greendale, Harare
A9: ID | B9: Date | C9: Description | D9: Debit | E9: Credit | F9: Balance | J9: ID | K9: Date | L9: Description | M9: Debit | N9: Credit | O9: Balance | R9: LeaseID | S9: Tenant | T9: Balance B/F | U9: Amount Charged | V9: Amount Due | W9: Amount Paid | X9: Carried Forward
C10: Balance brought forward | F10: 57.9 | L10: Balance brought forward | O10: 0 | R10: 5817 | S10: Agnes Furidze 1 Coronation | T10: -50 | U10: 50 | V10: 0 | W10: 0 | X10: 0
A11: 1282723 | B11: 45567 | C11: Payment Leaseid-5833 Emeldah Paradza 16 Coronation Ref-LEVY - 16 CORONATION | E11: 50 | F11: 107.9 | M11: 0 | N11: 0 | O11: 0 | R11: 5819 | S11: Eva Mutangadura 2 Coronation | T11: 0 | U11: 50 | V11: 50 | W11: 50 | X11: 0
A12: 1282726 | B12: 45567 | C12: Levy Commission Leaseid-5833 Ref-LEVY - 16 CORONATION | D12: 7.51 | F12: 100.39 | R12: 5820 | S12: Kudzanayi Kachere 3 Coronation | T12: 50 | U12: 50 | V12: 100 | W12: 0 | X12: 100
A13: 1282730 | B13: 45567 | C13: Payment Leaseid-5834 Margaret Mushayi 17 Coronation Ref-LEVY - 17 CORONATION | E13: 50 | F13: 150.39 | R13: 5821 | S13: Hebros Dubai 4 Coronation | T13: 0 | U13: 50 | V13: 50 | W13: 0 | X13: 50
A14: 1282733 | B14: 45567 | C14: Levy Commission Leaseid-5834 Ref-LEVY - 17 CORONATION | D14: 7.51 | F14: 142.88 | R14: 5822 | S14: Tatenda Ngowe 5 Coronation | T14: 0 | U14: 50 | V14: 50 | W14: 0 | X14: 50
A15: 1282737 | B15: 45567 | C15: Payment Leaseid-5828 Farai Chivaura 11 Coronation Ref-LEVY - 11 CORONATION | E15: 50 | F15: 192.88 | R15: 5823 | S15: Maud Silibaziso 6 Coronation | T15: 0 | U15: 50 | V15: 50 | W15: 0 | X15: 50
A16: 1282740 | B16: 45567 | C16: Levy Commission Leaseid-5828 Ref-LEVY - 11 CORONATION | D16: 7.51 | F16: 185.37 | R16: 5824 | S16: Gibson Taruwinga 7 Coronation | T16: 0 | U16: 50 | V16: 50 | W16: 50 | X16: 0
A17: 1282744 | B17: 45567 | C17: Payment Leaseid-5824 Gibson Taruwinga 7 Coronation Ref-LEVY - 7 CORONATION | E17: 50 | F17: 235.37 | R17: 5825 | S17: Lody Machiwenyika 8 Coronation | T17: 0 | U17: 50 | V17: 50 | W17: 0 | X17: 50
A18: 1282747 | B18: 45567 | C18: Levy Commission Leaseid-5824 Ref-LEVY - 7 CORONATION | D18: 7.51 | F18: 227.86 | R18: 5826 | S18: Unit 9 Coronation Gardens | T18: 50 | U18: 50 | V18: 100 | W18: 100 | X18: 0
A19: 1282751 | B19: 45567 | C19: Payment Leaseid-5826 Unit 9 Coronation Gardens Ref-LEVY - 9 CORONATION | E19: 100 | F19: 327.86 | R19: 5827 | S19: Dorothy R. S Makoni 10 Coronation | T19: 0 | U19: 50 | V19: 50 | W19: 0 | X19: 50
A20: 1282754 | B20: 45567 | C20: Levy Commission Leaseid-5826 Ref-LEVY - 9 CORONATION | D20: 15.01 | F20: 312.85 | R20: 5828 | S20: Farai Chivaura 11 Coronation | T20: 0 | U20: 50 | V20: 50 | W20: 50 | X20: 0
A21: 1282758 | B21: 45567 | C21: Payment Leaseid-5832 Toko Muodzi Ross 15 Coronation Gardens Ref-LEVY - 15 CORONATION | E21: 50 | F21: 362.85 | R21: 5829 | S21: Rose Chanakira 12 Coronation | T21: 0 | U21: 50 | V21: 50 | W21: 0 | X21: 50
A22: 1282761 | B22: 45567 | C22: Levy Commission Leaseid-5832 Ref-LEVY - 15 CORONATION | D22: 7.51 | F22: 355.34 | R22: 5830 | S22: Siketiwe Marima 13 Coronation | T22: -100 | U22: 50 | V22: -50 | W22: 0 | X22: -50
A23: 1282765 | B23: 45567 | C23: Payment Leaseid-5831 Phillers Gwengo 14 Coronation Ref-LEVY - 14 CORONATION | E23: 50 | F23: 405.34 | R23: 5831 | S23: Phillers Gwengo 14 Coronation | T23: 0 | U23: 50 | V23: 50 | W23: 50 | X23: 0
A24: 1282768 | B24: 45567 | C24: Levy Commission Leaseid-5831 Ref-LEVY - 14 CORONATION | D24: 7.51 | F24: 397.83 | R24: 5832 | S24: Toko Muodzi Ross 15 Coronation Gardens | T24: 0 | U24: 50 | V24: 50 | W24: 50 | X24: 0
A25: 1282772 | B25: 45567 | C25: Payment Leaseid-5819 Eva Mutangadura 2 Coronation Ref-LEVY - 2 CORONATION | E25: 50 | F25: 447.83 | R25: 5833 | S25: Emeldah Paradza 16 Coronation | T25: 0 | U25: 50 | V25: 50 | W25: 50 | X25: 0
A26: 1282775 | B26: 45567 | C26: Levy Commission Leaseid-5819 Ref-LEVY - 2 CORONATION | D26: 7.51 | F26: 440.32 | R26: 5834 | S26: Margaret Mushayi 17 Coronation | T26: 0 | U26: 50 | V26: 50 | W26: 50 | X26: 0
A27: 1311639 | B27: 45596 | C27: Payment Ref-KWARIRIMA LOVEMORE-SALARY | D27: 180 | F27: 260.32 | T27: -50 | U27: 850 | V27: 800 | W27: 450 | X27: 350
A28: 1311810 | B28: 45596 | C28: Journal ref-STAFF SALARIES | D28: 363 | F28: -102.68 | X28: =X22 -> -50
D29: 610.58 | E29: 450 | F29: -102.68 | X29: =X28*-1 -> 50
X30: =X27+X29 -> 400

Sheet September
A1: Statement | I1: Statement | R1: Roll Over Summary
R2: landlord - Coronation Gardens Onwers Association
A3: Account Holder: Coronation Gardens Onwers Association | I3: Account Holder: Coronation Gardens Onwers Association | R3: Period: 2024-09-01 to 2024-09-30
R4: Currency: USD
A5: Account ID:58345 | I5: Account ID:58344
A6: Account Currency:USD | I6: Account Currency:ZIG
A7: Transaction Period:2024-09-01 - 2024-09-30 | I7: Transaction Period:2024-09-01 - 2024-09-30
R8: Property - Coronation Gardens, Greendale, Harare
A9: ID | B9: Date | C9: Description | D9: Debit | E9: Credit | F9: Balance | I9: ID | J9: Date | K9: Description | L9: Debit | M9: Credit | N9: Balance | R9: LeaseID | S9: Tenant | T9: Balance B/F | U9: Amount Charged | V9: Amount Due | W9: Amount Paid | X9: Carried Forward
C10: Balance brought forward | F10: 8.56 | K10: Balance brought forward | N10: 0 | R10: 5817 | S10: Agnes Furidze 1 Coronation | T10: 0 | U10: 50 | V10: 50 | W10: 100 | X10: -50
A11: 1260426 | B11: 45537 | C11: Payment Leaseid-5833 Emeldah Paradza 16 Coronation Ref-LEVY - 16 CORONATION | E11: 50 | F11: 58.56 | L11: 0 | M11: 0 | N11: 0 | R11: 5819 | S11: Eva Mutangadura 2 Coronation | T11: 0 | U11: 50 | V11: 50 | W11: 50 | X11: 0
A12: 1260430 | B12: 45537 | C12: Levy Commission Leaseid-5833 Ref-LEVY - 16 CORONATION | D12: 7.51 | F12: 51.05 | R12: 5820 | S12: Kudzanayi Kachere 3 Coronation | T12: 0 | U12: 50 | V12: 50 | W12: 0 | X12: 50
A13: 1260589 | B13: 45537 | C13: Payment Leaseid-5828 Farai Chivaura 11 Coronation Ref-LEVY - 11 CORONATION | E13: 50 | F13: 101.05 | R13: 5821 | S13: Hebros Dubai 4 Coronation | T13: 0 | U13: 50 | V13: 50 | W13: 50 | X13: 0
A14: 1260593 | B14: 45537 | C14: Levy Commission Leaseid-5828 Ref-LEVY - 11 CORONATION | D14: 7.51 | F14: 93.54 | R14: 5822 | S14: Tatenda Ngowe 5 Coronation | T14: 0 | U14: 50 | V14: 50 | W14: 50 | X14: 0
A15: 1264114 | B15: 45538 | C15: Payment Leaseid-5825 Lody Machiwenyika 8 Coronation Ref-LEVY - 8 CORONATION | E15: 50 | F15: 143.54 | R15: 5823 | S15: Maud Silibaziso 6 Coronation | T15: 50 | U15: 50 | V15: 100 | W15: 100 | X15: 0
A16: 1264117 | B16: 45538 | C16: Levy Commission Leaseid-5825 Ref-LEVY - 8 CORONATION | D16: 7.51 | F16: 136.03 | R16: 5824 | S16: Gibson Taruwinga 7 Coronation | T16: 0 | U16: 50 | V16: 50 | W16: 50 | X16: 0
A17: 1264121 | B17: 45538 | C17: Payment Leaseid-5827 Dorothy R. S Makoni 10 Coronation Ref-LEVY - 10 CORONATION | E17: 50 | F17: 186.03 | R17: 5825 | S17: Lody Machiwenyika 8 Coronation | T17: 0 | U17: 50 | V17: 50 | W17: 50 | X17: 0
A18: 1264124 | B18: 45538 | C18: Levy Commission Leaseid-5827 Ref-LEVY - 10 CORONATION | D18: 7.51 | F18: 178.52 | R18: 5826 | S18: Unit 9 Coronation Gardens | T18: 50 | U18: 50 | V18: 100 | W18: 50 | X18: 50
A19: 1264128 | B19: 45538 | C19: Payment Leaseid-5834 Margaret Mushayi 17 Coronation Ref-LEVY - 17 CORONATION | E19: 50 | F19: 228.52 | R19: 5827 | S19: Dorothy R. S Makoni 10 Coronation | T19: 0 | U19: 50 | V19: 50 | W19: 50 | X19: 0
A20: 1264131 | B20: 45538 | C20: Levy Commission Leaseid-5834 Ref-LEVY - 17 CORONATION | D20: 7.51 | F20: 221.01 | R20: 5828 | S20: Farai Chivaura 11 Coronation | T20: 0 | U20: 50 | V20: 50 | W20: 50 | X20: 0
A21: 1264135 | B21: 45538 | C21: Payment Leaseid-5829 Rose Chanakira 12 Coronation Ref-LEVY - 12 CORONATION | E21: 50 | F21: 271.01 | R21: 5829 | S21: Rose Chanakira 12 Coronation | T21: 0 | U21: 50 | V21: 50 | W21: 50 | X21: 0
A22: 1264138 | B22: 45538 | C22: Levy Commission Leaseid-5829 Ref-LEVY - 12 CORONATION | D22: 7.51 | F22: 263.5 | R22: 5830 | S22: Siketiwe Marima 13 Coronation | T22: -50 | U22: 50 | V22: 0 | W22: 100 | X22: -100
A23: 1264142 | B23: 45538 | C23: Payment Leaseid-5832 Toko Muodzi Ross 15 Coronation Gardens Ref-LEVY - 15 CORONATION | E23: 50 | F23: 313.5 | R23: 5831 | S23: Phillers Gwengo 14 Coronation | T23: 0 | U23: 50 | V23: 50 | W23: 50 | X23: 0
A24: 1264145 | B24: 45538 | C24: Levy Commission Leaseid-5832 Ref-LEVY - 15 CORONATION | D24: 7.51 | F24: 305.99 | R24: 5832 | S24: Toko Muodzi Ross 15 Coronation Gardens | T24: 0 | U24: 50 | V24: 50 | W24: 50 | X24: 0
A25: 1264149 | B25: 45538 | C25: Payment Leaseid-5830 Siketiwe Marima 13 Coronation Ref-LEVY - 13 CORONATION | E25: 100 | F25: 405.99 | R25: 5833 | S25: Emeldah Paradza 16 Coronation | T25: 0 | U25: 50 | V25: 50 | W25: 50 | X25: 0
A26: 1264152 | B26: 45538 | C26: Levy Commission Leaseid-5830 Ref-LEVY - 13 CORONATION | D26: 15.01 | F26: 390.98 | R26: 5834 | S26: Margaret Mushayi 17 Coronation | T26: 0 | U26: 50 | V26: 50 | W26: 50 | X26: 0
A27: 1264156 | B27: 45538 | C27: Payment Leaseid-5831 Phillers Gwengo 14 Coronation Ref-LEVY - 14 CORONATION | E27: 50 | F27: 440.98 | T27: 50 | U27: 850 | V27: 900 | W27: 950 | X27: -50
A28: 1264159 | B28: 45538 | C28: Levy Commission Leaseid-5831 Ref-LEVY - 14 CORONATION | D28: 7.51 | F28: 433.47 | X28: =X10+X22 -> -150
A29: 1264163 | B29: 45538 | C29: Payment Leaseid-5824 Gibson Taruwinga 7 Coronation Ref-LEVY - 7 CORONATION | E29: 50 | F29: 483.47 | X29: =X28*-1 -> 150
A30: 1264166 | B30: 45538 | C30: Levy Commission Leaseid-5824 Ref-LEVY - 7 CORONATION | D30: 7.51 | F30: 475.96 | X30: =X29+X27 -> 100
A31: 1264170 | B31: 45538 | C31: Payment Leaseid-5826 Unit 9 Coronation Gardens Ref-LEVY - 9 CORONATION | E31: 50 | F31: 525.96
A32: 1264173 | B32: 45538 | C32: Levy Commission Leaseid-5826 Ref-LEVY - 9 CORONATION | D32: 7.51 | F32: 518.45
A33: 1264177 | B33: 45538 | C33: Payment Leaseid-5822 Tatenda Ngowe 5 Coronation Ref-LEVY - 5 CORONATION | E33: 50 | F33: 568.45
A34: 1264180 | B34: 45538 | C34: Levy Commission Leaseid-5822 Ref-LEVY - 5 CORONATION | D34: 7.51 | F34: 560.94
A35: 1264184 | B35: 45538 | C35: Payment Leaseid-5819 Eva Mutangadura 2 Coronation Ref-LEVY - 2 CORONATION | E35: 50 | F35: 610.94
A36: 1264187 | B36: 45538 | C36: Levy Commission Leaseid-5819 Ref-LEVY - 2 CORONATION | D36: 7.51 | F36: 603.43
A37: 1271494 | B37: 45541 | C37: Payment Ref-UTILITIES-MURARA BROOM & RAKE | D37: 10 | F37: 693.43
A38: 1270373 | B38: 45546 | C38: Payment Leaseid-5817 Agnes Furidze 1 Coronation Ref-SEPT&OCT LEVY - 1 CORONATION/transfer 23.8.24 | E38: 100 | F38: 693.43
A39: 1270376 | B39: 45546 | C39: Levy Commission Leaseid-5817 Ref-SEPT&OCT LEVY - 1 CORONATION/transfer 23.8.24 | D39: 15.01 | F39: 678.42
A40: 1273752 | B40: 45554 | C40: Payment Leaseid-5823 Maud Silibaziso 6 Coronation Ref-LEVY - 6 CORONATION | E40: 100 | F40: 778.42
A41: 1273755 | B41: 45554 | C41: Levy Commission Leaseid-5823 Ref-LEVY - 6 CORONATION | D41: 15.01 | F41: 763.41
A42: 1274593 | B42: 45554 | C42: Payment Ref-CONEX MIRROR | D42: 215 | F42: 548.41
A43: 1275829 | B43: 45559 | C43: Payment Leaseid-5821 Hebros Dubai 4 Coronation Ref-LEVY-DUBAI D-4 CORONATION-24/09/24-CASH | E43: 50 | F43: 598.41
A44: 1275832 | B44: 45559 | C44: Levy Commission Leaseid-5821 Ref-LEVY-DUBAI D-4 CORONATION-24/09/24-CASH | D44: 7.51 | F44: 590.9
A45: 1280621 | B45: 45565 | C45: Payment Ref-STAFF SALARIES | D45: 533 | F45: 57.9
D46: 900.66 | E46: 950 | F46: 57.9

Sheet August
A1: Statement | J1: Statement | R1: Roll Over Summary
R2: landlord - Coronation Gardens Onwers Association
A3: Account Holder: Coronation Gardens Onwers Association | J3: Account Holder: Coronation Gardens Onwers Association | R3: Period: 2024-08-01 to 2024-08-31
R4: Currency: USD
A5: Account ID:58345 | J5: Account ID:58344
A6: Account Currency:USD | J6: Account Currency:ZIG
A7: Transaction Period:2024-08-01 - 2024-08-31 | J7: Transaction Period:2024-08-01 - 2024-08-31
R8: Property - Coronation Gardens, Greendale, Harare
A9: ID | B9: Date | C9: Description | D9: Debit | E9: Credit | F9: Balance | J9: ID | K9: Date | L9: Description | M9: Debit | N9: Credit | O9: Balance | R9: LeaseID | S9: Tenant | T9: Balance B/F | U9: Amount Charged | V9: Amount Due | W9: Amount Paid | X9: Carried Forward
C10: Balance brought forward | F10: 286.61 | L10: Balance brought forward | O10: 0 | R10: 5817 | S10: Agnes Furidze 1 Coronation | T10: -50 | U10: 50 | V10: 0 | W10: 0 | X10: 0
A11: 1232770 | B11: 45505 | C11: Payment Leaseid-5825 Lody Machiwenyika 8 Coronation Ref-LEVY - 8 CORONATION | E11: 50 | F11: 336.61 | M11: 0 | N11: 0 | O11: 0 | R11: 5819 | S11: Eva Mutangadura 2 Coronation | T11: -50 | U11: 50 | V11: 0 | W11: 0 | X11: 0
A12: 1232773 | B12: 45505 | C12: Levy Commission Leaseid-5825 Ref-LEVY - 8 CORONATION | D12: 7.51 | F12: 329.1 | R12: 5820 | S12: Kudzanayi Kachere 3 Coronation | T12: 0 | U12: 50 | V12: 50 | W12: 50 | X12: 0
A13: 1232777 | B13: 45505 | C13: Payment Leaseid-5826 Unit 9 Coronation Gardens Ref-LEVY - 9 CORONATION | E13: 50 | F13: 379.1 | R13: 5821 | S13: Hebros Dubai 4 Coronation | T13: 50 | U13: 50 | V13: 100 | W13: 100 | X13: 0
A14: 1232780 | B14: 45505 | C14: Levy Commission Leaseid-5826 Ref-LEVY - 9 CORONATION | D14: 7.51 | F14: 371.59 | R14: 5822 | S14: Tatenda Ngowe 5 Coronation | T14: -50 | U14: 50 | V14: 0 | W14: 0 | X14: 0
A15: 1249515 | B15: 45523 | C15: Payment Leaseid-5820 Kudzanayi Kachere 3 Coronation Ref-LEVY-KACHERE K-3 CORONATION-TRANSFER-07/08/24 | E15: 50 | F15: 421.59 | R15: 5823 | S15: Maud Silibaziso 6 Coronation | T15: 0 | U15: 50 | V15: 50 | W15: 0 | X15: 50
A16: 1249518 | B16: 45523 | C16: Levy Commission Leaseid-5820 Ref-LEVY-KACHERE K-3 CORONATION-TRANSFER-07/08/24 | D16: 7.51 | F16: 414.08 | R16: 5824 | S16: Gibson Taruwinga 7 Coronation | T16: 0 | U16: 50 | V16: 50 | W16: 50 | X16: 0
A17: 1250603 | B17: 45525 | C17: Payment Leaseid-5824 Gibson Taruwinga 7 Coronation Ref-LEVY-TARUWINGA G-7 CORONATION-TRANSFER-09/08/24 | E17: 50 | F17: 464.08 | R17: 5825 | S17: Lody Machiwenyika 8 Coronation | T17: 0 | U17: 50 | V17: 50 | W17: 50 | X17: 0
A18: 1250606 | B18: 45525 | C18: Levy Commission Leaseid-5824 Ref-LEVY-TARUWINGA G-7 CORONATION-TRANSFER-09/08/24 | D18: 7.51 | F18: 456.57 | R18: 5826 | S18: Unit 9 Coronation Gardens | T18: 50 | U18: 50 | V18: 100 | W18: 50 | X18: 50
A19: 1253005 | B19: 45532 | C19: Payment Leaseid-5821 Hebros Dubai 4 Coronation Ref-LEVY 4 CORONATION DUBAI CASH 28/8/24 | E19: 100 | F19: 556.57 | R19: 5827 | S19: Dorothy R. S Makoni 10 Coronation | T19: -50 | U19: 50 | V19: 0 | W19: 0 | X19: 0
A20: 1253008 | B20: 45532 | C20: Levy Commission Leaseid-5821 Ref-LEVY 4 CORONATION DUBAI CASH 28/8/24 | D20: 15.01 | F20: 541.56 | R20: 5828 | S20: Farai Chivaura 11 Coronation | T20: -50 | U20: 50 | V20: 0 | W20: 0 | X20: 0
A21: 1263906 | B21: 45534 | C21: Payment Ref-STAFF SALARIES | D21: 533 | F21: 58.56 | G21: =F20-D21 -> 8.56 | R21: 5829 | S21: Rose Chanakira 12 Coronation | T21: -50 | U21: 50 | V21: 0 | W21: 0 | X21: 0
D22: 578.05 | E22: 300 | F22: 58.56 | R22: 5830 | S22: Siketiwe Marima 13 Coronation | T22: -100 | U22: 50 | V22: -50 | W22: 0 | X22: -50
R23: 5831 | S23: Phillers Gwengo 14 Coronation | T23: -50 | U23: 50 | V23: 0 | W23: 0 | X23: 0
R24: 5832 | S24: Toko Muodzi Ross 15 Coronation Gardens | T24: -50 | U24: 50 | V24: 0 | W24: 0 | X24: 0
R25: 5833 | S25: Emeldah Paradza 16 Coronation | T25: -50 | U25: 50 | V25: 0 | W25: 0 | X25: 0
R26: 5834 | S26: Margaret Mushayi 17 Coronation | T26: -50 | U26: 50 | V26: 0 | W26: 0 | X26: 0
T27: -500 | U27: 850 | V27: 350 | W27: 300 | X27: 50
X28: =X22 -> -50
X29: =X28*-1 -> 50
X30: =X27+X29 -> 100

Sheet july 25
A1: Statement | J1: Statement | S1: Roll Over Summary
S2: landlord - Coronation Gardens Onwers Association
A3: Account Holder: Coronation Gardens Onwers Association | J3: Account Holder: Coronation Gardens Onwers Association | S3: Period: 2025-07-01 to 2025-07-31
S4: Currency: USD
A5: Account ID:58345 | J5: Account ID:58344
A6: Account Currency:USD | J6: Account Currency:ZIG
A7: Transaction Period:2025-07-01 - 2025-07-31 | J7: Transaction Period:2025-07-01 - 2025-07-31
S8: Property - Coronation Gardens, Greendale, Harare
A9: ID | B9: Date | C9: Description | D9: Debit | E9: Credit | F9: Balance | J9: ID | K9: Date | L9: Description | M9: Debit | N9: Credit | O9: Balance | S9: LeaseID | T9: Tenant | U9: Balance B/F | V9: Amount Charged | W9: Amount Due | X9: Amount Paid | Y9: Carried Forward
C10: Balance brought forward | F10: -291 | L10: Balance brought forward | O10: 0 | S10: 5817 | T10: Agnes Furidze 1 Coronation | U10: -50 | V10: 50 | W10: 0 | X10: 0 | Y10: 0
A11: 1391128 | B11: 45839 | C11: Payment Leaseid-5820 Kudzanayi Kachere 3 Coronation Ref-LEVY-KACHERE K-3 CORONATION-TRANSFER-27/06/25 | E11: 50 | F11: -241 | M11: 0 | N11: 0 | O11: 0 | S11: 5819 | T11: Eva Mutangadura 2 Coronation | U11: 0 | V11: 50 | W11: 50 | X11: 50 | Y11: 0
A12: 1391131 | B12: 45839 | C12: Levy Commission Leaseid-5820 Ref-LEVY-KACHERE K-3 CORONATION-TRANSFER-27/06/25 | D12: 7.51 | F12: -248.51 | S12: 5820 | T12: Kudzanayi Kachere 3 Coronation | U12: 0 | V12: 190 | W12: 190 | X12: 240 | Y12: -50
A13: 1393636 | B13: 45841 | C13: Payment Leaseid-5830 Siketiwe Marima 13 Coronation Ref-LEVY - 13 CORONATION VILLAS | E13: 50 | F13: -198.51 | S13: 5821 | T13: Hebros Dubai 4 Coronation | U13: 20 | V13: 50 | W13: 70 | X13: 50 | Y13: 20
A14: 1393639 | B14: 45841 | C14: Levy Commission Leaseid-5830 Ref-LEVY - 13 CORONATION VILLAS | D14: 7.51 | F14: -206.02 | S14: 5822 | T14: Tatenda Ngowe 5 Coronation | U14: 0 | V14: 50 | W14: 50 | X14: 0 | Y14: 50
A15: 1393643 | B15: 45841 | C15: Payment Leaseid-5832 Toko Muodzi Ross 15 Coronation Gardens Ref-LEVY - 15 CORONATION VILLAS | E15: 50 | F15: -156.02 | S15: 5823 | T15: Maud Silibaziso 6 Coronation | U15: 68 | V15: 50 | W15: 118 | X15: 58 | Y15: 60
A16: 1393646 | B16: 45841 | C16: Levy Commission Leaseid-5832 Ref-LEVY - 15 CORONATION VILLAS | D16: 7.51 | F16: -163.53 | S16: 5824 | T16: Gibson Taruwinga 7 Coronation | U16: 0 | V16: 50 | W16: 50 | X16: 50 | Y16: 0
A17: 1393661 | B17: 45841 | C17: Payment Leaseid-5833 Emeldah Paradza 16 Coronation Ref-LEVY - 16 CORONATION GARDENS | E17: 50 | F17: -113.53 | S17: 5825 | T17: Lody Machiwenyika 8 Coronation | U17: 0 | V17: 50 | W17: 50 | X17: 0 | Y17: 50
A18: 1393664 | B18: 45841 | C18: Levy Commission Leaseid-5833 Ref-LEVY - 16 CORONATION GARDENS | D18: 7.51 | F18: -121.04 | S18: 5826 | T18: Unit 9 Coronation Gardens | U18: 50 | V18: 50 | W18: 100 | X18: 50 | Y18: 50
A19: 1393668 | B19: 45841 | C19: Payment Leaseid-5834 Margaret Mushayi 17 Coronation Ref-LEVY - 17 CORONATION GARDENS | E19: 50 | F19: -71.04 | S19: 5827 | T19: Dorothy R. S Makoni 10 Coronation | U19: 50 | V19: 50 | W19: 100 | X19: 100 | Y19: 0
A20: 1393671 | B20: 45841 | C20: Levy Commission Leaseid-5834 Ref-LEVY - 17 CORONATION GARDENS | D20: 7.51 | F20: -78.55 | S20: 5828 | T20: Farai Chivaura 11 Coronation | U20: 0 | V20: 50 | W20: 50 | X20: 0 | Y20: 50
A21: 1393675 | B21: 45841 | C21: Payment Leaseid-5831 Phillers Gwengo 14 Coronation Ref-LEVY - 14 CORONATION GARDENS | E21: 50 | F21: -28.55 | S21: 5829 | T21: Rose Chanakira 12 Coronation | U21: -50 | V21: 50 | W21: 0 | X21: 0 | Y21: 0
A22: 1393678 | B22: 45841 | C22: Levy Commission Leaseid-5831 Ref-LEVY - 14 CORONATION GARDENS | D22: 7.51 | F22: -36.06 | S22: 5830 | T22: Siketiwe Marima 13 Coronation | U22: 0 | V22: 50 | W22: 50 | X22: 50 | Y22: 0
A23: 1393682 | B23: 45841 | C23: Payment Leaseid-5823 Maud Silibaziso 6 Coronation Ref-LEVY - 6 CORONATION GARDENS | E23: 58 | F23: 21.94 | S23: 5831 | T23: Phillers Gwengo 14 Coronation | U23: 0 | V23: 50 | W23: 50 | X23: 50 | Y23: 0
A24: 1393685 | B24: 45841 | C24: Levy Commission Leaseid-5823 Ref-LEVY - 6 CORONATION GARDENS | D24: 8.71 | F24: 13.23 | S24: 5832 | T24: Toko Muodzi Ross 15 Coronation Gardens | U24: 0 | V24: 50 | W24: 50 | X24: 50 | Y24: 0
A25: 1393689 | B25: 45841 | C25: Payment Leaseid-5824 Gibson Taruwinga 7 Coronation Ref-LEVY - 7 CORONATION GARDENS | E25: 50 | F25: 63.23 | S25: 5833 | T25: Emeldah Paradza 16 Coronation | U25: 0 | V25: 50 | W25: 50 | X25: 50 | Y25: 0
A26: 1393692 | B26: 45841 | C26: Levy Commission Leaseid-5824 Ref-LEVY - 7 CORONATION GARDENS | D26: 7.51 | F26: 55.72 | S26: 5834 | T26: Margaret Mushayi 17 Coronation | U26: 0 | V26: 50 | W26: 50 | X26: 50 | Y26: 0
A27: 1393696 | B27: 45841 | C27: Payment Leaseid-5826 Unit 9 Coronation Gardens Ref-LEVY - 9 CORONATION GARDENS | E27: 50 | F27: 105.72 | U27: 88 | V27: 990 | W27: 1078 | X27: 848 | Y27: 230
A28: 1393699 | B28: 45841 | C28: Levy Commission Leaseid-5826 Ref-LEVY - 9 CORONATION GARDENS | D28: 7.51 | F28: 98.21 | Y28: =Y12*-1 -> 50
A29: 1393703 | B29: 45841 | C29: Payment Leaseid-5819 Eva Mutangadura 2 Coronation Ref-LEVY - 2 CORONATION GARDENS | E29: 50 | F29: 148.21 | Y29: =Y28+Y27 -> 280
A30: 1393706 | B30: 45841 | C30: Levy Commission Leaseid-5819 Ref-LEVY - 2 CORONATION GARDENS | D30: 7.51 | F30: 140.7
A31: 1393710 | B31: 45841 | C31: Payment Leaseid-5820 Kudzanayi Kachere 3 Coronation Ref-LEVY - 3 CORONATION GARDENS | E31: 140 | F31: 280.7
A32: 1393713 | B32: 45841 | C32: Levy Commission Leaseid-5820 Ref-LEVY - 3 CORONATION GARDENS | D32: 21.01 | F32: 259.69
A33: 1393865 | B33: 45841 | C33: Payment Ref-WORKSUITS & SAFETY SHOES | D33: 67 | F33: 192.69
A34: 1401077 | B34: 45841 | C34: Journal ref-mispost reversed-3 Coronation | D34: 140 | F34: 52.69
A35: 1401081 | B35: 45841 | C35: Journal ref-mispost reversed-commission-3 Coronation | E35: 21.01 | F35: 73.7
A36: 1395379 | B36: 45845 | C36: Payment Leaseid-5821 Hebros Dubai 4 Coronation Ref-LEVY - 4 CORONATION GARDENS | E36: 50 | F36: 123.7
A37: 1395382 | B37: 45845 | C37: Levy Commission Leaseid-5821 Ref-LEVY - 4 CORONATION GARDENS | D37: 7.51 | F37: 116.19
A38: 1395767 | B38: 45845 | C38: Payment Leaseid-5820 Kudzanayi Kachere 3 Coronation Ref-LEVY-KACHERE K-3 CORONATION-TRANSFER-27/06/25 | E38: 50 | F38: 166.19
A39: 1395770 | B39: 45845 | C39: Levy Commission Leaseid-5820 Ref-LEVY-KACHERE K-3 CORONATION-TRANSFER-27/06/25 | D39: 7.51 | F39: 158.68
A40: 1396851 | B40: 45846 | C40: Payment Leaseid-5827 Dorothy R. S Makoni 10 Coronation Ref-LEVY-MAKONI D-10 CORONATION-ECOCASH-03/07/25 | E40: 100 | F40: 258.68
A41: 1396854 | B41: 45846 | C41: Levy Commission Leaseid-5827 Ref-LEVY-MAKONI D-10 CORONATION-ECOCASH-03/07/25 | D41: 15.01 | F41: 243.67
A42: 1399856 | B42: 45853 | C42: Payment Ref-GATE REPAIRS | D42: 63 | F42: 180.67
A43: 1404550 | B43: 45869 | C43: Journal ref-STAFF SALARIES | D43: 543 | F43: -362.33
D44: 940.34 | E44: =869.01-E35-E31 -> 708 | F44: -362.33

Sheet JUNE
A1: Statement | J1: Statement | R1: Roll Over Summary
R2: landlord - Coronation Gardens Onwers Association
A3: Account Holder: Coronation Gardens Onwers Association | J3: Account Holder: Coronation Gardens Onwers Association | R3: Period: 2024-06-01 to 2024-06-30
R4: Currency: USD
A5: Account ID:58345 | J5: Account ID:58344
A6: Account Currency:USD | J6: Account Currency:ZIG
A7: Transaction Period:2024-06-01 - 2024-06-30 | J7: Transaction Period:2024-06-01 - 2024-06-30
R8: Property - Coronation Gardens, Greendale, Harare
A9: ID | B9: Date | C9: Description | D9: Debit | E9: Credit | F9: Balance | J9: ID | K9: Date | L9: Description | M9: Debit | N9: Credit | O9: Balance | R9: LeaseID | S9: Tenant | T9: Balance B/F | U9: Amount Charged | V9: Amount Due | W9: Amount Paid | X9: Carried Forward
C10: Balance brought forward | F10: 0 | L10: Balance brought forward | O10: 0 | R10: 5817 | S10: Agnes Furidze 1 Coronation | T10: 50 | U10: 50 | V10: 100 | W10: 50 | X10: 0
A11: 1224933 | B11: 45444 | C11: Journal ref-cash received from previous management team-Coronation Gardens | E11: 400 | F11: 400 | M11: 0 | N11: 0 | O11: 0 | R11: 5819 | S11: Eva Mutangadura 2 Coronation | T11: 50 | U11: 50 | V11: 200 | W11: 100 | X11: -50
A12: 1203534 | B12: 45454 | C12: Payment Leaseid-5817 Agnes Furidze 1 Coronation Ref-LEVY - 1 CORONATION | E12: 50 | F12: 450 | R12: 5820 | S12: Kudzanayi Kachere 3 Coronation | T12: 50 | U12: 50 | V12: 300 | W12: 50 | X12: 0
A13: 1203537 | B13: 45454 | C13: Levy Commission Leaseid-5817 Ref-LEVY - 1 CORONATION | D13: 7.51 | F13: 442.49 | H13: =E12*0.1501 -> 7.505 | R13: 5821 | S13: Hebros Dubai 4 Coronation | T13: 50 | U13: 150 | V13: 500 | W13: 150 | X13: 0
A14: 1203541 | B14: 45454 | C14: Payment Leaseid-5819 Eva Mutangadura 2 Coronation Ref-LEVY - 2 CORONATION | E14: 50 | F14: 492.49 | R14: 5822 | S14: Tatenda Ngowe 5 Coronation | T14: 50 | U14: 50 | V14: 600 | W14: 50 | X14: 0
A15: 1203544 | B15: 45454 | C15: Levy Commission Leaseid-5819 Ref-LEVY - 2 CORONATION | D15: 7.51 | F15: 484.98 | R15: 5823 | S15: Maud Silibaziso 6 Coronation | T15: 50 | U15: 50 | V15: 700 | W15: 100 | X15: -50
A16: 1203548 | B16: 45454 | C16: Payment Leaseid-5820 Kudzanayi Kachere 3 Coronation Ref-LEVY - 3 CORONATION | E16: 50 | F16: 534.98 | R16: 5824 | S16: Gibson Taruwinga 7 Coronation | T16: 50 | U16: 50 | V16: 800 | W16: 100 | X16: -50
A17: 1203551 | B17: 45454 | C17: Levy Commission Leaseid-5820 Ref-LEVY - 3 CORONATION | D17: 7.51 | F17: 527.47 | R17: 5825 | S17: Lody Machiwenyika 8 Coronation | T17: 50 | U17: 50 | V17: 900 | W17: 100 | X17: -50
A18: 1203557 | B18: 45454 | C18: Payment Leaseid-5821 Hebros Dubai 4 Coronation Ref-LEVY - 4 CORONATION | E18: 100 | F18: 627.47 | R18: 5826 | S18: Unit 9 Coronation Gardens | T18: 50 | U18: 50 | V18: 1000 | W18: 50 | X18: 0
A19: 1203560 | B19: 45454 | C19: Levy Commission Leaseid-5821 Ref-LEVY - 4 CORONATION | D19: 15.01 | F19: 612.46 | R19: 5827 | S19: Dorothy R. S Makoni 10 Coronation | T19: 50 | U19: 50 | V19: 1100 | W19: 100 | X19: -50
A20: 1203564 | B20: 45454 | C20: Payment Leaseid-5822 Tatenda Ngowe 5 Coronation Ref-LEVY - 5 CORONATION | E20: 50 | F20: 662.46 | R20: 5828 | S20: Farai Chivaura 11 Coronation | T20: 50 | U20: 50 | V20: 1200 | W20: 100 | X20: -50
A21: 1203567 | B21: 45454 | C21: Levy Commission Leaseid-5822 Ref-LEVY - 5 CORONATION | D21: 7.51 | F21: 654.95 | R21: 5829 | S21: Rose Chanakira 12 Coronation | T21: 50 | U21: 50 | V21: 1300 | W21: 100 | X21: -50
A22: 1203573 | B22: 45454 | C22: Payment Leaseid-5823 Maud Silibaziso 6 Coronation Ref-LEVY - 6 CORONATION | E22: 50 | F22: 704.95 | R22: 5830 | S22: Siketiwe Marima 13 Coronation | T22: 50 | U22: 50 | V22: 1400 | W22: 200 | X22: -150
A23: 1203576 | B23: 45454 | C23: Levy Commission Leaseid-5823 Ref-LEVY - 6 CORONATION | D23: 7.51 | F23: 697.44 | R23: 5831 | S23: Phillers Gwengo 14 Coronation | T23: 50 | U23: 50 | V23: 1500 | W23: 100 | X23: -50
A24: 1203580 | B24: 45454 | C24: Payment Leaseid-5824 Gibson Taruwinga 7 Coronation Ref-LEVY - 7 CORONATION | E24: 100 | F24: 797.44 | R24: 5832 | S24: Toko Muodzi Ross 15 Coronation Gardens | T24: 50 | U24: 50 | V24: 1600 | W24: 100 | X24: -50
A25: 1203583 | B25: 45454 | C25: Levy Commission Leaseid-5824 Ref-LEVY - 7 CORONATION | D25: 15.01 | F25: 782.43 | R25: 5833 | S25: Emeldah Paradza 16 Coronation | T25: 50 | U25: 50 | V25: 1700 | W25: 100 | X25: -50
A26: 1203587 | B26: 45454 | C26: Payment Leaseid-5825 Lody Machiwenyika 8 Coronation Ref-LEVY - 8 CORONATION | E26: 50 | F26: 832.43 | R26: 5834 | S26: Margaret Mushayi 17 Coronation | T26: 50 | U26: 50 | V26: 1800 | W26: 100 | X26: -50
A27: 1203590 | B27: 45454 | C27: Levy Commission Leaseid-5825 Ref-LEVY - 8 CORONATION | D27: 7.51 | F27: 824.92 | T27: 850 | U27: 950 | V27: 1800 | W27: 1650 | X27: -700
A28: 1203594 | B28: 45454 | C28: Payment Leaseid-5827 Dorothy R. S Makoni 10 Coronation Ref-LEVY - 10 CORONATION | E28: 50 | F28: 874.92 | X28: =X11+X15+X16+X17+X19+X20+X21+X22+X23+X24+X25+X26 -> -700
A29: 1203597 | B29: 45454 | C29: Levy Commission Leaseid-5827 Ref-LEVY - 10 CORONATION | D29: 7.51 | F29: 867.41 | X29: =X28*-1 -> 700
A30: 1203601 | B30: 45454 | C30: Payment Leaseid-5828 Farai Chivaura 11 Coronation Ref-LEVY - 11 CORONATION | E30: 50 | F30: 917.41 | X30: 0
A31: 1203604 | B31: 45454 | C31: Levy Commission Leaseid-5828 Ref-LEVY - 11 CORONATION | D31: 7.51 | F31: 909.9
A32: 1203608 | B32: 45454 | C32: Payment Leaseid-5829 Rose Chanakira 12 Coronation Ref-LEVY - 12 CORONATION | E32: 50 | F32: 959.9
A33: 1203611 | B33: 45454 | C33: Levy Commission Leaseid-5829 Ref-LEVY - 12 CORONATION | D33: 7.51 | F33: 952.39
A34: 1203615 | B34: 45454 | C34: Payment Leaseid-5830 Siketiwe Marima 13 Coronation Ref-LEVY - 13 CORONATION | E34: 200 | F34: 1152.39
A35: 1203618 | B35: 45454 | C35: Levy Commission Leaseid-5830 Ref-LEVY - 13 CORONATION | D35: 30.02 | F35: 1122.37
A36: 1203624 | B36: 45454 | C36: Payment Leaseid-5831 Phillers Gwengo 14 Coronation Ref-LEVY - 14 CORONATION | E36: 50 | F36: 1172.37
A37: 1203627 | B37: 45454 | C37: Levy Commission Leaseid-5831 Ref-LEVY - 14 CORONATION | D37: 7.51 | F37: 1164.86
A38: 1203631 | B38: 45454 | C38: Payment Leaseid-5832 Toko Muodzi Ross 15 Coronation Gardens Ref-LEVY - 15 CORONATION | E38: 50 | F38: 1214.86
A39: 1203634 | B39: 45454 | C39: Levy Commission Leaseid-5832 Ref-LEVY - 15 CORONATION | D39: 7.51 | F39: 1207.35
A40: 1203638 | B40: 45454 | C40: Payment Leaseid-5833 Emeldah Paradza 16 Coronation Ref-LEVY - 16 CORONATION | E40: 50 | F40: 1257.35
A41: 1203641 | B41: 45454 | C41: Levy Commission Leaseid-5833 Ref-LEVY - 16 CORONATION | D41: 7.51 | F41: 1249.84
A42: 1203645 | B42: 45454 | C42: Payment Leaseid-5834 Margaret Mushayi 17 Coronation Ref-LEVY - 17 CORONATION | E42: 50 | F42: 1299.84
A43: 1203648 | B43: 45454 | C43: Levy Commission Leaseid-5834 Ref-LEVY - 17 CORONATION | D43: 7.51 | F43: 1292.33
A44: 1205294 | B44: 45454 | C44: Payment Leaseid-5821 Hebros Dubai 4 Coronation Ref-LEVY-4 CORONATION | E44: 50 | F44: 1342.33
A45: 1205297 | B45: 45454 | C45: Levy Commission Leaseid-5821 Ref-LEVY-4 CORONATION | D45: 7.51 | F45: 1334.82
A46: 1205300 | B46: 45454 | C46: Journal ref-mispost reversed | D46: 100 | F46: 1234.82
A47: 1205304 | B47: 45454 | C47: Journal ref-mispost reversed-4 Coronation commission & vat | E47: 15.01 | F47: 1249.83
A48: 1204760 | B48: 45455 | C48: Payment Ref-STAFF SALARIES | D48: 533 | F48: 716.83
A49: 1204762 | B49: 45455 | C49: Payment Ref-ZESA PURCHASE | D49: 50 | F49: 666.83
A50: 1204764 | B50: 45455 | C50: Payment Ref-RACK ALIGNMENT | D50: 40 | F50: 626.83
A51: 1204766 | B51: 45455 | C51: Payment Ref-ROAD REPAIRS | D51: 24 | F51: 602.83
A52: 1204768 | B52: 45455 | C52: Journal ref-GATE REPAIRS | D52: 270 | F52: 332.83
A53: 1210125 | B53: 45471 | C53: Payment Leaseid-5828 Farai Chivaura 11 Coronation Ref-LEVY - 11 CORONATION | E53: 50 | F53: 382.83
A54: 1210128 | B54: 45471 | C54: Levy Commission Leaseid-5828 Ref-LEVY - 11 CORONATION | D54: 7.51 | F54: 375.32
A55: 1210132 | B55: 45471 | C55: Payment Leaseid-5827 Dorothy R. S Makoni 10 Coronation Ref-LEVY - 10 CORONATION | E55: 50 | F55: 425.32
A56: 1210135 | B56: 45471 | C56: Levy Commission Leaseid-5827 Ref-LEVY - 10 CORONATION | D56: 7.51 | F56: 417.81
A57: 1210139 | B57: 45471 | C57: Payment Leaseid-5834 Margaret Mushayi 17 Coronation Ref-LEVY - 17 CORONATION | E57: 50 | F57: 467.81
A58: 1210142 | B58: 45471 | C58: Levy Commission Leaseid-5834 Ref-LEVY - 17 CORONATION | D58: 7.51 | F58: 460.3
A59: 1210146 | B59: 45471 | C59: Payment Leaseid-5829 Rose Chanakira 12 Coronation Ref-LEVY - 12 CORONATION | E59: 50 | F59: 510.3
A60: 1210149 | B60: 45471 | C60: Levy Commission Leaseid-5829 Ref-LEVY - 12 CORONATION | D60: 7.51 | F60: 502.79
A61: 1210153 | B61: 45471 | C61: Payment Leaseid-5832 Toko Muodzi Ross 15 Coronation Gardens Ref-LEVY - 15 CORONATION | E61: 50 | F61: 552.79
A62: 1210156 | B62: 45471 | C62: Levy Commission Leaseid-5832 Ref-LEVY - 15 CORONATION | D62: 7.51 | F62: 545.28
A63: 1210160 | B63: 45471 | C63: Payment Leaseid-5831 Phillers Gwengo 14 Coronation Ref-LEVY - 14 CORONATION | E63: 50 | F63: 595.28
A64: 1210163 | B64: 45471 | C64: Levy Commission Leaseid-5831 Ref-LEVY - 14 CORONATION | D64: 7.51 | F64: 587.77
A65: 1210167 | B65: 45471 | C65: Payment Leaseid-5823 Maud Silibaziso 6 Coronation Ref-LEVY - 6 CORONATION | E65: 50 | F65: 637.77
A66: 1210170 | B66: 45471 | C66: Levy Commission Leaseid-5823 Ref-LEVY - 6 CORONATION | D66: 7.51 | F66: 630.26
A67: 1210174 | B67: 45471 | C67: Payment Leaseid-5826 Unit 9 Coronation Gardens Ref-LEVY - 9 CORONATION | E67: 50 | F67: 680.26
A68: 1210177 | B68: 45471 | C68: Levy Commission Leaseid-5826 Ref-LEVY - 9 CORONATION | D68: 7.51 | F68: 672.75
A69: 1210181 | B69: 45471 | C69: Payment Leaseid-5825 Lody Machiwenyika 8 Coronation Ref-LEVY - 8 CORONATION | E69: 50 | F69: 722.75
A70: 1210184 | B70: 45471 | C70: Levy Commission Leaseid-5825 Ref-LEVY - 8 CORONATION | D70: 7.51 | F70: 715.24
A71: 1210188 | B71: 45471 | C71: Payment Leaseid-5819 Eva Mutangadura 2 Coronation Ref-LEVY - 2 CORONATION | E71: 50 | F71: 765.24
A72: 1210191 | B72: 45471 | C72: Levy Commission Leaseid-5819 Ref-LEVY - 2 CORONATION | D72: 7.51 | F72: 757.73
A73: 1210195 | B73: 45471 | C73: Payment Leaseid-5833 Emeldah Paradza 16 Coronation Ref-LEVY - 16 CORONATION | E73: 50 | F73: 807.73
A74: 1210198 | B74: 45471 | C74: Levy Commission Leaseid-5833 Ref-LEVY - 16 CORONATION | D74: 7.51 | F74: 800.22
D75: 1264.79 | E75: =2065.01-E11-E24-E47 -> 1550 | F75: 800.22
D76: =D75-D46-D25 -> 1149.78
